{
  "meta": {
    "accepted_with_shortfall": false,
    "attempts_total": 112,
    "elapsed_total_s": 0.44161295890808105,
    "found": 100,
    "group": "panda_arm",
    "ik_successes_total": 112,
    "ik_timeout_s": 0.1,
    "named_start_for_seeding": "ready",
    "nullspace_jitter": 0.02,
    "nullspace_step": 0.2,
    "num_spaces": 10,
    "pass_metas": [
      {
        "attempts": 112,
        "elapsed_s": 0.44136524200439453,
        "found": 100,
        "group": "panda_arm",
        "ik_successes": 112,
        "ik_timeout_s": 0.1,
        "named_start_for_seeding": "ready",
        "nullspace_jitter": 0.02,
        "nullspace_step": 0.2,
        "num_spaces": 10,
        "pass_index": 0,
        "requested": 100,
        "rng": {
          "deterministic_joint_seeds": true,
          "engine": "numpy.default_rng",
          "note": "Avoid MoveIt internal RNG (RobotState.set_to_random_positions)."
        },
        "seed": 201008,
        "seed_pass": 201008,
        "target_point": {
          "x": 0.14219310504239474,
          "y": -0.004881379054485005,
          "z": 0.16140484062072843
        },
        "tip_link": "panda_link8",
        "uniq_resolution_rad": 0.001,
        "yaw_range_rad": 6.283185307179586
      }
    ],
    "pass_seed_stride": 100000,
    "passes_requested": 3,
    "passes_used": 1,
    "precheck_attempts": 56,
    "precheck_found": 50,
    "precheck_ik_successes": 56,
    "precheck_max_attempts": 1200,
    "precheck_num_spaces": 8,
    "reason": "ok",
    "requested": 100,
    "resample_max": 200,
    "resample_trial_final": 1,
    "resample_trials_used": 1,
    "seed": 201008,
    "shortfall": 0,
    "target_point": {
      "x": 0.14219310504239474,
      "y": -0.004881379054485005,
      "z": 0.16140484062072843
    },
    "tip_link": "panda_link8",
    "uniq_resolution_rad": 0.001,
    "yaw_range_rad": 6.283185307179586
  },
  "solutions": [
    {
      "attempt": 1,
      "attempt_global": 1,
      "index": 0,
      "joint_names": [
        "panda_joint1",
        "panda_joint2",
        "panda_joint3",
        "panda_joint4",
        "panda_joint5",
        "panda_joint6",
        "panda_joint7"
      ],
      "joint_positions": [
        2.2902631500162625,
        -0.05669382275278828,
        -1.8922396431754331,
        -3.0713299794754683,
        2.3417899644849007,
        3.216620145977498,
        2.149447110427469
      ],
      "pass_index": 0,
      "pass_seed": 201008,
      "sampled_yaw_rad": -2.9730813718150495,
      "target_point": {
        "x": 0.14219310504239474,
        "y": -0.004881379054485005,
        "z": 0.16140484062072843
      },
      "tip_link": "panda_link8"
    },
    {
      "attempt": 2,
      "attempt_global": 2,
      "index": 1,
      "joint_names": [
        "panda_joint1",
        "panda_joint2",
        "panda_joint3",
        "panda_joint4",
        "panda_joint5",
        "panda_joint6",
        "panda_joint7"
      ],
      "joint_positions": [
        2.3600757075814633,
        -0.05920224243183445,
        -1.9818020203740705,
        -3.0606461251498827,
        2.3823802945369734,
        3.220467257372224,
        2.0888001776884364
      ],
      "pass_index": 0,
      "pass_seed": 201008,
      "sampled_yaw_rad": -2.9730813718150495,
      "target_point": {
        "x": 0.14219310504239474,
        "y": -0.004881379054485005,
        "z": 0.16140484062072843
      },
      "tip_link": "panda_link8"
    },
    {
      "attempt": 3,
      "attempt_global": 3,
      "index": 2,
      "joint_names": [
        "panda_joint1",
        "panda_joint2",
        "panda_joint3",
        "panda_joint4",
        "panda_joint5",
        "panda_joint6",
        "panda_joint7"
      ],
      "joint_positions": [
        2.612813069568542,
        -0.06867357496468855,
        -2.3310857399483056,
        -3.0163234270877424,
        2.572490085827186,
        3.233997568071801,
        1.801223591750223
      ],
      "pass_index": 0,
      "pass_seed": 201008,
      "sampled_yaw_rad": -2.9730813718150495,
      "target_point": {
        "x": 0.14219310504239474,
        "y": -0.004881379054485005,
        "z": 0.16140484062072843
      },
      "tip_link": "panda_link8"
    },
    {
      "attempt": 4,
      "attempt_global": 4,
      "index": 3,
      "joint_names": [
        "panda_joint1",
        "panda_joint2",
        "panda_joint3",
        "panda_joint4",
        "panda_joint5",
        "panda_joint6",
        "panda_joint7"
      ],
      "joint_positions": [
        0.624107090278517,
        0.06250816065082326,
        -1.0419316300321873,
        -3.0459306650188473,
        -2.441018332586636,
        3.2253501229142634,
        -0.16230571219128256
      ],
      "pass_index": 0,
      "pass_seed": 201008,
      "sampled_yaw_rad": -2.9730813718150495,
      "target_point": {
        "x": 0.14219310504239474,
        "y": -0.004881379054485005,
        "z": 0.16140484062072843
      },
      "tip_link": "panda_link8"
    },
    {
      "attempt": 5,
      "attempt_global": 5,
      "index": 4,
      "joint_names": [
        "panda_joint1",
        "panda_joint2",
        "panda_joint3",
        "panda_joint4",
        "panda_joint5",
        "panda_joint6",
        "panda_joint7"
      ],
      "joint_positions": [
        2.28707591480892,
        -0.05658100147981762,
        -1.8882064760424422,
        -3.0718,
        2.3400373292395553,
        3.216444022944439,
        2.1520595284172446
      ],
      "pass_index": 0,
      "pass_seed": 201008,
      "sampled_yaw_rad": -2.9730813718150495,
      "target_point": {
        "x": 0.14219310504239474,
        "y": -0.004881379054485005,
        "z": 0.16140484062072843
      },
      "tip_link": "panda_link8"
    },
    {
      "attempt": 6,
      "attempt_global": 6,
      "index": 5,
      "joint_names": [
        "panda_joint1",
        "panda_joint2",
        "panda_joint3",
        "panda_joint4",
        "panda_joint5",
        "panda_joint6",
        "panda_joint7"
      ],
      "joint_positions": [
        -0.8545724566653335,
        0.05657881686751722,
        1.2534536706526138,
        -3.0718,
        2.3400142429234707,
        3.216441478052828,
        2.152094584850095
      ],
      "pass_index": 0,
      "pass_seed": 201008,
      "sampled_yaw_rad": -2.9730813718150495,
      "target_point": {
        "x": 0.14219310504239474,
        "y": -0.004881379054485005,
        "z": 0.16140484062072843
      },
      "tip_link": "panda_link8"
    },
    {
      "attempt": 9,
      "attempt_global": 9,
      "index": 6,
      "joint_names": [
        "panda_joint1",
        "panda_joint2",
        "panda_joint3",
        "panda_joint4",
        "panda_joint5",
        "panda_joint6",
        "panda_joint7"
      ],
      "joint_positions": [
        2.6436245901966924,
        -0.06979038577635696,
        -2.3767858275014393,
        -3.010620395887467,
        2.6007631580012336,
        3.235511526626675,
        1.7580144918396896
      ],
      "pass_index": 0,
      "pass_seed": 201008,
      "sampled_yaw_rad": -2.9730813718150495,
      "target_point": {
        "x": 0.14219310504239474,
        "y": -0.004881379054485005,
        "z": 0.16140484062072843
      },
      "tip_link": "panda_link8"
    },
    {
      "attempt": 11,
      "attempt_global": 11,
      "index": 7,
      "joint_names": [
        "panda_joint1",
        "panda_joint2",
        "panda_joint3",
        "panda_joint4",
        "panda_joint5",
        "panda_joint6",
        "panda_joint7"
      ],
      "joint_positions": [
        0.6324187660222607,
        0.06219678314810679,
        -1.0531410971747117,
        -3.047346100543206,
        -2.435245153405615,
        3.224897470157221,
        -0.17101095474050867
      ],
      "pass_index": 0,
      "pass_seed": 201008,
      "sampled_yaw_rad": -2.9730813718150495,
      "target_point": {
        "x": 0.14219310504239474,
        "y": -0.004881379054485005,
        "z": 0.16140484062072843
      },
      "tip_link": "panda_link8"
    },
    {
      "attempt": 12,
      "attempt_global": 12,
      "index": 8,
      "joint_names": [
        "panda_joint1",
        "panda_joint2",
        "panda_joint3",
        "panda_joint4",
        "panda_joint5",
        "panda_joint6",
        "panda_joint7"
      ],
      "joint_positions": [
        2.418009632932451,
        -0.06133822332661525,
        -2.058127852920254,
        -3.051193535079527,
        2.4196408926793076,
        3.2236490090681906,
        2.032894013845172
      ],
      "pass_index": 0,
      "pass_seed": 201008,
      "sampled_yaw_rad": -2.9730813718150495,
      "target_point": {
        "x": 0.14219310504239474,
        "y": -0.004881379054485005,
        "z": 0.16140484062072843
      },
      "tip_link": "panda_link8"
    },
    {
      "attempt": 13,
      "attempt_global": 13,
      "index": 9,
      "joint_names": [
        "panda_joint1",
        "panda_joint2",
        "panda_joint3",
        "panda_joint4",
        "panda_joint5",
        "panda_joint6",
        "panda_joint7"
      ],
      "joint_positions": [
        2.646108281691608,
        -0.06987927808272497,
        -2.380501552929364,
        -3.0101616468485353,
        2.603092230419713,
        3.235631415540969,
        1.754450598687479
      ],
      "pass_index": 0,
      "pass_seed": 201008,
      "sampled_yaw_rad": -2.9730813718150495,
      "target_point": {
        "x": 0.14219310504239474,
        "y": -0.004881379054485005,
        "z": 0.16140484062072843
      },
      "tip_link": "panda_link8"
    },
    {
      "attempt": 14,
      "attempt_global": 14,
      "index": 10,
      "joint_names": [
        "panda_joint1",
        "panda_joint2",
        "panda_joint3",
        "panda_joint4",
        "panda_joint5",
        "panda_joint6",
        "panda_joint7"
      ],
      "joint_positions": [
        2.8972999853472996,
        -0.07730630785512017,
        -2.7802376018524573,
        -2.9691402132461313,
        2.8748382298670916,
        3.245358460809792,
        1.9617380768650718
      ],
      "pass_index": 0,
      "pass_seed": 201008,
      "sampled_yaw_rad": -2.34631506618967,
      "target_point": {
        "x": 0.14219310504239474,
        "y": -0.004881379054485005,
        "z": 0.16140484062072843
      },
      "tip_link": "panda_link8"
    },
    {
      "attempt": 15,
      "attempt_global": 15,
      "index": 11,
      "joint_names": [
        "panda_joint1",
        "panda_joint2",
        "panda_joint3",
        "panda_joint4",
        "panda_joint5",
        "panda_joint6",
        "panda_joint7"
      ],
      "joint_positions": [
        2.7948415890462415,
        -0.07473460513208782,
        -2.6116677266758854,
        -2.983949910843192,
        2.7558114652516057,
        3.242059528401306,
        2.1462556198821594
      ],
      "pass_index": 0,
      "pass_seed": 201008,
      "sampled_yaw_rad": -2.34631506618967,
      "target_point": {
        "x": 0.14219310504239474,
        "y": -0.004881379054485005,
        "z": 0.16140484062072843
      },
      "tip_link": "panda_link8"
    },
    {
      "attempt": 17,
      "attempt_global": 17,
      "index": 12,
      "joint_names": [
        "panda_joint1",
        "panda_joint2",
        "panda_joint3",
        "panda_joint4",
        "panda_joint5",
        "panda_joint6",
        "panda_joint7"
      ],
      "joint_positions": [
        2.739097263420416,
        -0.07303336283812445,
        -2.5231344838371457,
        -2.993325209074141,
        2.695821160407527,
        3.239867152039452,
        2.238875639982823
      ],
      "pass_index": 0,
      "pass_seed": 201008,
      "sampled_yaw_rad": -2.34631506618967,
      "target_point": {
        "x": 0.14219310504239474,
        "y": -0.004881379054485005,
        "z": 0.16140484062072843
      },
      "tip_link": "panda_link8"
    },
    {
      "attempt": 18,
      "attempt_global": 18,
      "index": 13,
      "joint_names": [
        "panda_joint1",
        "panda_joint2",
        "panda_joint3",
        "panda_joint4",
        "panda_joint5",
        "panda_joint6",
        "panda_joint7"
      ],
      "joint_positions": [
        2.3622964339863453,
        -0.0592762993238897,
        -1.9846719001505042,
        -3.0603049080456137,
        2.383708157554124,
        3.220581993267779,
        2.713580021227851
      ],
      "pass_index": 0,
      "pass_seed": 201008,
      "sampled_yaw_rad": -2.34631506618967,
      "target_point": {
        "x": 0.14219310504239474,
        "y": -0.004881379054485005,
        "z": 0.16140484062072843
      },
      "tip_link": "panda_link8"
    },
    {
      "attempt": 19,
      "attempt_global": 19,
      "index": 14,
      "joint_names": [
        "panda_joint1",
        "panda_joint2",
        "panda_joint3",
        "panda_joint4",
        "panda_joint5",
        "panda_joint6",
        "panda_joint7"
      ],
      "joint_positions": [
        2.7221011229438443,
        -0.07249119593128198,
        -2.4964807123917367,
        -2.9963535681224,
        2.6778820786391373,
        3.2391154632026007,
        2.2664429361013942
      ],
      "pass_index": 0,
      "pass_seed": 201008,
      "sampled_yaw_rad": -2.34631506618967,
      "target_point": {
        "x": 0.14219310504239474,
        "y": -0.004881379054485005,
        "z": 0.16140484062072843
      },
      "tip_link": "panda_link8"
    },
    {
      "attempt": 21,
      "attempt_global": 21,
      "index": 15,
      "joint_names": [
        "panda_joint1",
        "panda_joint2",
        "panda_joint3",
        "panda_joint4",
        "panda_joint5",
        "panda_joint6",
        "panda_joint7"
      ],
      "joint_positions": [
        2.789160853975316,
        -0.07456983703246171,
        -2.602536037889459,
        -2.984872744320499,
        2.749530001998028,
        3.2418472840741175,
        2.1559661823198977
      ],
      "pass_index": 0,
      "pass_seed": 201008,
      "sampled_yaw_rad": -2.34631506618967,
      "target_point": {
        "x": 0.14219310504239474,
        "y": -0.004881379054485005,
        "z": 0.16140484062072843
      },
      "tip_link": "panda_link8"
    },
    {
      "attempt": 22,
      "attempt_global": 22,
      "index": 16,
      "joint_names": [
        "panda_joint1",
        "panda_joint2",
        "panda_joint3",
        "panda_joint4",
        "panda_joint5",
        "panda_joint6",
        "panda_joint7"
      ],
      "joint_positions": [
        0.7618850159242423,
        0.05742663458078112,
        -1.2229286356085767,
        -3.068237622492538,
        -2.3533898996232527,
        3.217760161726136,
        0.3330120835594764
      ],
      "pass_index": 0,
      "pass_seed": 201008,
      "sampled_yaw_rad": -2.34631506618967,
      "target_point": {
        "x": 0.14219310504239474,
        "y": -0.004881379054485005,
        "z": 0.16140484062072843
      },
      "tip_link": "panda_link8"
    },
    {
      "attempt": 23,
      "attempt_global": 23,
      "index": 17,
      "joint_names": [
        "panda_joint1",
        "panda_joint2",
        "panda_joint3",
        "panda_joint4",
        "panda_joint5",
        "panda_joint6",
        "panda_joint7"
      ],
      "joint_positions": [
        2.8164494833873905,
        -0.07534168946161088,
        -2.6466200222896457,
        -2.980522176911252,
        2.7800322948617544,
        3.2428410640021745,
        2.108785521129133
      ],
      "pass_index": 0,
      "pass_seed": 201008,
      "sampled_yaw_rad": -2.34631506618967,
      "target_point": {
        "x": 0.14219310504239474,
        "y": -0.004881379054485005,
        "z": 0.16140484062072843
      },
      "tip_link": "panda_link8"
    },
    {
      "attempt": 24,
      "attempt_global": 24,
      "index": 18,
      "joint_names": [
        "panda_joint1",
        "panda_joint2",
        "panda_joint3",
        "panda_joint4",
        "panda_joint5",
        "panda_joint6",
        "panda_joint7"
      ],
      "joint_positions": [
        2.586052096840632,
        -0.06768628425415732,
        -2.291981788550771,
        -3.0212755132844014,
        2.5488650145055995,
        3.232646673109749,
        2.4640166834166295
      ],
      "pass_index": 0,
      "pass_seed": 201008,
      "sampled_yaw_rad": -2.34631506618967,
      "target_point": {
        "x": 0.14219310504239474,
        "y": -0.004881379054485005,
        "z": 0.16140484062072843
      },
      "tip_link": "panda_link8"
    },
    {
      "attempt": 26,
      "attempt_global": 26,
      "index": 19,
      "joint_names": [
        "panda_joint1",
        "panda_joint2",
        "panda_joint3",
        "panda_joint4",
        "panda_joint5",
        "panda_joint6",
        "panda_joint7"
      ],
      "joint_positions": [
        2.9037644642839764,
        -0.07744229987133779,
        -2.791085019591819,
        -2.9683376652451647,
        2.882656072096009,
        3.2455317291255437,
        1.9495898315328735
      ],
      "pass_index": 0,
      "pass_seed": 201008,
      "sampled_yaw_rad": -2.34631506618967,
      "target_point": {
        "x": 0.14219310504239474,
        "y": -0.004881379054485005,
        "z": 0.16140484062072843
      },
      "tip_link": "panda_link8"
    },
    {
      "attempt": 27,
      "attempt_global": 27,
      "index": 20,
      "joint_names": [
        "panda_joint1",
        "panda_joint2",
        "panda_joint3",
        "panda_joint4",
        "panda_joint5",
        "panda_joint6",
        "panda_joint7"
      ],
      "joint_positions": [
        2.8973,
        -0.07730630713257966,
        -2.7802379749705026,
        -2.969140181614451,
        2.874838489048367,
        3.245358463343981,
        2.729854995452065
      ],
      "pass_index": 0,
      "pass_seed": 201008,
      "sampled_yaw_rad": -1.5781977553800173,
      "target_point": {
        "x": 0.14219310504239474,
        "y": -0.004881379054485005,
        "z": 0.16140484062072843
      },
      "tip_link": "panda_link8"
    },
    {
      "attempt": 28,
      "attempt_global": 28,
      "index": 21,
      "joint_names": [
        "panda_joint1",
        "panda_joint2",
        "panda_joint3",
        "panda_joint4",
        "panda_joint5",
        "panda_joint6",
        "panda_joint7"
      ],
      "joint_positions": [
        2.2870387733521698,
        -0.05658011673264727,
        -1.8881596849547848,
        -3.0718,
        2.340018320411603,
        3.2164425487475046,
        -2.7362133762063308
      ],
      "pass_index": 0,
      "pass_seed": 201008,
      "sampled_yaw_rad": -1.5781977553800173,
      "target_point": {
        "x": 0.14219310504239474,
        "y": -0.004881379054485005,
        "z": 0.16140484062072843
      },
      "tip_link": "panda_link8"
    },
    {
      "attempt": 30,
      "attempt_global": 30,
      "index": 22,
      "joint_names": [
        "panda_joint1",
        "panda_joint2",
        "panda_joint3",
        "panda_joint4",
        "panda_joint5",
        "panda_joint6",
        "panda_joint7"
      ],
      "joint_positions": [
        2.8342029268294278,
        -0.07581668831979824,
        -2.675588098698936,
        -2.9778139447070444,
        2.800303527529616,
        3.243450484014755,
        2.8455093864928185
      ],
      "pass_index": 0,
      "pass_seed": 201008,
      "sampled_yaw_rad": -1.5781977553800173,
      "target_point": {
        "x": 0.14219310504239474,
        "y": -0.004881379054485005,
        "z": 0.16140484062072843
      },
      "tip_link": "panda_link8"
    },
    {
      "attempt": 31,
      "attempt_global": 31,
      "index": 23,
      "joint_names": [
        "panda_joint1",
        "panda_joint2",
        "panda_joint3",
        "panda_joint4",
        "panda_joint5",
        "panda_joint6",
        "panda_joint7"
      ],
      "joint_positions": [
        0.6635669915517263,
        0.061020862958666586,
        -1.0949248126897826,
        -3.0526291925994102,
        -2.413897324654576,
        3.2231795784137884,
        1.1917553227959718
      ],
      "pass_index": 0,
      "pass_seed": 201008,
      "sampled_yaw_rad": -1.5781977553800173,
      "target_point": {
        "x": 0.14219310504239474,
        "y": -0.004881379054485005,
        "z": 0.16140484062072843
      },
      "tip_link": "panda_link8"
    },
    {
      "attempt": 32,
      "attempt_global": 32,
      "index": 24,
      "joint_names": [
        "panda_joint1",
        "panda_joint2",
        "panda_joint3",
        "panda_joint4",
        "panda_joint5",
        "panda_joint6",
        "panda_joint7"
      ],
      "joint_positions": [
        -2.473170092763694,
        -0.06083942806957005,
        2.0402155853692956,
        -3.0534367113858645,
        -2.4106785156588257,
        3.2229120948561625,
        1.1869186918801837
      ],
      "pass_index": 0,
      "pass_seed": 201008,
      "sampled_yaw_rad": -1.5781977553800173,
      "target_point": {
        "x": 0.14219310504239474,
        "y": -0.004881379054485005,
        "z": 0.16140484062072843
      },
      "tip_link": "panda_link8"
    },
    {
      "attempt": 33,
      "attempt_global": 33,
      "index": 25,
      "joint_names": [
        "panda_joint1",
        "panda_joint2",
        "panda_joint3",
        "panda_joint4",
        "panda_joint5",
        "panda_joint6",
        "panda_joint7"
      ],
      "joint_positions": [
        -0.8545232369907585,
        0.05658077205146201,
        1.253394354028102,
        -3.0718,
        2.3400338960279727,
        3.216443678461399,
        -2.7362370233073245
      ],
      "pass_index": 0,
      "pass_seed": 201008,
      "sampled_yaw_rad": -1.5781977553800173,
      "target_point": {
        "x": 0.14219310504239474,
        "y": -0.004881379054485005,
        "z": 0.16140484062072843
      },
      "tip_link": "panda_link8"
    },
    {
      "attempt": 34,
      "attempt_global": 34,
      "index": 26,
      "joint_names": [
        "panda_joint1",
        "panda_joint2",
        "panda_joint3",
        "panda_joint4",
        "panda_joint5",
        "panda_joint6",
        "panda_joint7"
      ],
      "joint_positions": [
        -2.3730437592905362,
        -0.05719039035371489,
        1.9101780206314005,
        -3.069236816448912,
        -2.349629184369984,
        3.217394222701164,
        1.0955174137494186
      ],
      "pass_index": 0,
      "pass_seed": 201008,
      "sampled_yaw_rad": -1.5781977553800173,
      "target_point": {
        "x": 0.14219310504239474,
        "y": -0.004881379054485005,
        "z": 0.16140484062072843
      },
      "tip_link": "panda_link8"
    },
    {
      "attempt": 35,
      "attempt_global": 35,
      "index": 27,
      "joint_names": [
        "panda_joint1",
        "panda_joint2",
        "panda_joint3",
        "panda_joint4",
        "panda_joint5",
        "panda_joint6",
        "panda_joint7"
      ],
      "joint_positions": [
        2.804711296706958,
        -0.07500995094672164,
        -2.6276166112603474,
        -2.9823609369100206,
        2.7668486069765246,
        3.2424214151719126,
        2.8972976708776645
      ],
      "pass_index": 0,
      "pass_seed": 201008,
      "sampled_yaw_rad": -1.5781977553800173,
      "target_point": {
        "x": 0.14219310504239474,
        "y": -0.004881379054485005,
        "z": 0.16140484062072843
      },
      "tip_link": "panda_link8"
    },
    {
      "attempt": 36,
      "attempt_global": 36,
      "index": 28,
      "joint_names": [
        "panda_joint1",
        "panda_joint2",
        "panda_joint3",
        "panda_joint4",
        "panda_joint5",
        "panda_joint6",
        "panda_joint7"
      ],
      "joint_positions": [
        -0.2258204340433017,
        0.07767697660884733,
        0.3302720531265035,
        -2.966928671899038,
        2.897298148664068,
        3.245833812409929,
        2.694941224125355
      ],
      "pass_index": 0,
      "pass_seed": 201008,
      "sampled_yaw_rad": -1.5781977553800173,
      "target_point": {
        "x": 0.14219310504239474,
        "y": -0.004881379054485005,
        "z": 0.16140484062072843
      },
      "tip_link": "panda_link8"
    },
    {
      "attempt": 38,
      "attempt_global": 38,
      "index": 29,
      "joint_names": [
        "panda_joint1",
        "panda_joint2",
        "panda_joint3",
        "panda_joint4",
        "panda_joint5",
        "panda_joint6",
        "panda_joint7"
      ],
      "joint_positions": [
        -2.3556626635981206,
        -0.05657865224619767,
        1.8881476103564043,
        -3.0718,
        -2.3400086558999327,
        3.2164412600499688,
        1.0811721294153336
      ],
      "pass_index": 0,
      "pass_seed": 201008,
      "sampled_yaw_rad": -1.5781977553800173,
      "target_point": {
        "x": 0.14219310504239474,
        "y": -0.004881379054485005,
        "z": 0.16140484062072843
      },
      "tip_link": "panda_link8"
    },
    {
      "attempt": 39,
      "attempt_global": 39,
      "index": 30,
      "joint_names": [
        "panda_joint1",
        "panda_joint2",
        "panda_joint3",
        "panda_joint4",
        "panda_joint5",
        "panda_joint6",
        "panda_joint7"
      ],
      "joint_positions": [
        2.8644003817088053,
        -0.07656942859377727,
        -2.725363765266337,
        -2.973461074561706,
        2.83553055782548,
        3.244416806177159,
        -2.786868764375432
      ],
      "pass_index": 0,
      "pass_seed": 201008,
      "sampled_yaw_rad": -0.8727726701808831,
      "target_point": {
        "x": 0.14219310504239474,
        "y": -0.004881379054485005,
        "z": 0.16140484062072843
      },
      "tip_link": "panda_link8"
    },
    {
      "attempt": 40,
      "attempt_global": 40,
      "index": 31,
      "joint_names": [
        "panda_joint1",
        "panda_joint2",
        "panda_joint3",
        "panda_joint4",
        "panda_joint5",
        "panda_joint6",
        "panda_joint7"
      ],
      "joint_positions": [
        2.8322572657997998,
        -0.07576565095309362,
        -2.6723999986454348,
        -2.978106200144655,
        2.7980610420201093,
        3.243384854493096,
        -2.7287766957230843
      ],
      "pass_index": 0,
      "pass_seed": 201008,
      "sampled_yaw_rad": -0.8727726701808831,
      "target_point": {
        "x": 0.14219310504239474,
        "y": -0.004881379054485005,
        "z": 0.16140484062072843
      },
      "tip_link": "panda_link8"
    },
    {
      "attempt": 41,
      "attempt_global": 41,
      "index": 32,
      "joint_names": [
        "panda_joint1",
        "panda_joint2",
        "panda_joint3",
        "panda_joint4",
        "panda_joint5",
        "panda_joint6",
        "panda_joint7"
      ],
      "joint_positions": [
        2.7167936275182965,
        -0.0723112513257712,
        -2.488289680401252,
        -2.9972749368383886,
        2.672607848530435,
        3.238901020240889,
        -2.535046257301527
      ],
      "pass_index": 0,
      "pass_seed": 201008,
      "sampled_yaw_rad": -0.8727726701808831,
      "target_point": {
        "x": 0.14219310504239474,
        "y": -0.004881379054485005,
        "z": 0.16140484062072843
      },
      "tip_link": "panda_link8"
    },
    {
      "attempt": 42,
      "attempt_global": 42,
      "index": 33,
      "joint_names": [
        "panda_joint1",
        "panda_joint2",
        "panda_joint3",
        "panda_joint4",
        "panda_joint5",
        "panda_joint6",
        "panda_joint7"
      ],
      "joint_positions": [
        2.8158534515410287,
        -0.07532633556438734,
        -2.6456445187065762,
        -2.980616613668669,
        2.779339750063019,
        3.242818362162665,
        -2.6997884749638765
      ],
      "pass_index": 0,
      "pass_seed": 201008,
      "sampled_yaw_rad": -0.8727726701808831,
      "target_point": {
        "x": 0.14219310504239474,
        "y": -0.004881379054485005,
        "z": 0.16140484062072843
      },
      "tip_link": "panda_link8"
    },
    {
      "attempt": 43,
      "attempt_global": 43,
      "index": 34,
      "joint_names": [
        "panda_joint1",
        "panda_joint2",
        "panda_joint3",
        "panda_joint4",
        "panda_joint5",
        "panda_joint6",
        "panda_joint7"
      ],
      "joint_positions": [
        2.7157731607331104,
        -0.07227741205982537,
        -2.486708154734066,
        -2.9974562325085508,
        2.6715690891118755,
        3.2388568466183876,
        -2.5334474550566317
      ],
      "pass_index": 0,
      "pass_seed": 201008,
      "sampled_yaw_rad": -0.8727726701808831,
      "target_point": {
        "x": 0.14219310504239474,
        "y": -0.004881379054485005,
        "z": 0.16140484062072843
      },
      "tip_link": "panda_link8"
    },
    {
      "attempt": 44,
      "attempt_global": 44,
      "index": 35,
      "joint_names": [
        "panda_joint1",
        "panda_joint2",
        "panda_joint3",
        "panda_joint4",
        "panda_joint5",
        "panda_joint6",
        "panda_joint7"
      ],
      "joint_positions": [
        2.287052813292842,
        -0.056580140200861065,
        -1.8881778603683275,
        -3.0718,
        2.3400262754947296,
        3.216442863922114,
        -2.0308004180244104
      ],
      "pass_index": 0,
      "pass_seed": 201008,
      "sampled_yaw_rad": -0.8727726701808831,
      "target_point": {
        "x": 0.14219310504239474,
        "y": -0.004881379054485005,
        "z": 0.16140484062072843
      },
      "tip_link": "panda_link8"
    },
    {
      "attempt": 45,
      "attempt_global": 45,
      "index": 36,
      "joint_names": [
        "panda_joint1",
        "panda_joint2",
        "panda_joint3",
        "panda_joint4",
        "panda_joint5",
        "panda_joint6",
        "panda_joint7"
      ],
      "joint_positions": [
        2.398281876677194,
        -0.06060631463791874,
        -2.0319231340929833,
        -3.0544714922103466,
        2.406568779982331,
        3.222567483455263,
        -2.130347827710712
      ],
      "pass_index": 0,
      "pass_seed": 201008,
      "sampled_yaw_rad": -0.8727726701808831,
      "target_point": {
        "x": 0.14219310504239474,
        "y": -0.004881379054485005,
        "z": 0.16140484062072843
      },
      "tip_link": "panda_link8"
    },
    {
      "attempt": 46,
      "attempt_global": 46,
      "index": 37,
      "joint_names": [
        "panda_joint1",
        "panda_joint2",
        "panda_joint3",
        "panda_joint4",
        "panda_joint5",
        "panda_joint6",
        "panda_joint7"
      ],
      "joint_positions": [
        0.22383588542225047,
        0.07619459200570043,
        -0.44139901261384995,
        -2.9756047842155726,
        -2.8177618419569384,
        3.243947925470322,
        2.515127364532277
      ],
      "pass_index": 0,
      "pass_seed": 201008,
      "sampled_yaw_rad": -0.8727726701808831,
      "target_point": {
        "x": 0.14219310504239474,
        "y": -0.004881379054485005,
        "z": 0.16140484062072843
      },
      "tip_link": "panda_link8"
    },
    {
      "attempt": 47,
      "attempt_global": 47,
      "index": 38,
      "joint_names": [
        "panda_joint1",
        "panda_joint2",
        "panda_joint3",
        "panda_joint4",
        "panda_joint5",
        "panda_joint6",
        "panda_joint7"
      ],
      "joint_positions": [
        -0.8545015912838284,
        0.05658167646733071,
        1.2533650472254685,
        -3.07179681604445,
        2.3400498892104697,
        3.216445317676966,
        -2.0308357268639408
      ],
      "pass_index": 0,
      "pass_seed": 201008,
      "sampled_yaw_rad": -0.8727726701808831,
      "target_point": {
        "x": 0.14219310504239474,
        "y": -0.004881379054485005,
        "z": 0.16140484062072843
      },
      "tip_link": "panda_link8"
    },
    {
      "attempt": 48,
      "attempt_global": 48,
      "index": 39,
      "joint_names": [
        "panda_joint1",
        "panda_joint2",
        "panda_joint3",
        "panda_joint4",
        "panda_joint5",
        "panda_joint6",
        "panda_joint7"
      ],
      "joint_positions": [
        2.8589078611579377,
        -0.07643897534549214,
        -2.7162571236843447,
        -2.9742207298317638,
        2.82904642548348,
        3.244249723956256,
        -2.7768079470496154
      ],
      "pass_index": 0,
      "pass_seed": 201008,
      "sampled_yaw_rad": -0.8727726701808831,
      "target_point": {
        "x": 0.14219310504239474,
        "y": -0.004881379054485005,
        "z": 0.16140484062072843
      },
      "tip_link": "panda_link8"
    },
    {
      "attempt": 49,
      "attempt_global": 49,
      "index": 40,
      "joint_names": [
        "panda_joint1",
        "panda_joint2",
        "panda_joint3",
        "panda_joint4",
        "panda_joint5",
        "panda_joint6",
        "panda_joint7"
      ],
      "joint_positions": [
        0.7858688418184365,
        0.05658153120093863,
        -1.2533651782836044,
        -3.0717976252624344,
        -2.3400469058799667,
        3.216444982018588,
        2.2728593474127483
      ],
      "pass_index": 0,
      "pass_seed": 201008,
      "sampled_yaw_rad": -0.3865678151646179,
      "target_point": {
        "x": 0.14219310504239474,
        "y": -0.004881379054485005,
        "z": 0.16140484062072843
      },
      "tip_link": "panda_link8"
    },
    {
      "attempt": 50,
      "attempt_global": 50,
      "index": 41,
      "joint_names": [
        "panda_joint1",
        "panda_joint2",
        "panda_joint3",
        "panda_joint4",
        "panda_joint5",
        "panda_joint6",
        "panda_joint7"
      ],
      "joint_positions": [
        -0.7450425997255071,
        0.06054194306493463,
        1.1119543599162174,
        -3.0547550046230763,
        2.4054479300266265,
        3.2224723400192175,
        -1.642461494295092
      ],
      "pass_index": 0,
      "pass_seed": 201008,
      "sampled_yaw_rad": -0.3865678151646179,
      "target_point": {
        "x": 0.14219310504239474,
        "y": -0.004881379054485005,
        "z": 0.16140484062072843
      },
      "tip_link": "panda_link8"
    },
    {
      "attempt": 51,
      "attempt_global": 51,
      "index": 42,
      "joint_names": [
        "panda_joint1",
        "panda_joint2",
        "panda_joint3",
        "panda_joint4",
        "panda_joint5",
        "panda_joint6",
        "panda_joint7"
      ],
      "joint_positions": [
        -2.4767283627478975,
        -0.06097233869129005,
        2.0449424921214003,
        -3.052845325480828,
        -2.4130347983789586,
        3.2231081069317473,
        2.3820890459885167
      ],
      "pass_index": 0,
      "pass_seed": 201008,
      "sampled_yaw_rad": -0.3865678151646179,
      "target_point": {
        "x": 0.14219310504239474,
        "y": -0.004881379054485005,
        "z": 0.16140484062072843
      },
      "tip_link": "panda_link8"
    },
    {
      "attempt": 52,
      "attempt_global": 52,
      "index": 43,
      "joint_names": [
        "panda_joint1",
        "panda_joint2",
        "panda_joint3",
        "panda_joint4",
        "panda_joint5",
        "panda_joint6",
        "panda_joint7"
      ],
      "joint_positions": [
        0.4280153449714964,
        0.06983773709594318,
        -0.7628303925419143,
        -3.0103761619839022,
        -2.6020020223938416,
        3.2355753992871965,
        2.668785714875325
      ],
      "pass_index": 0,
      "pass_seed": 201008,
      "sampled_yaw_rad": -0.3865678151646179,
      "target_point": {
        "x": 0.14219310504239474,
        "y": -0.004881379054485005,
        "z": 0.16140484062072843
      },
      "tip_link": "panda_link8"
    },
    {
      "attempt": 53,
      "attempt_global": 53,
      "index": 44,
      "joint_names": [
        "panda_joint1",
        "panda_joint2",
        "panda_joint3",
        "panda_joint4",
        "panda_joint5",
        "panda_joint6",
        "panda_joint7"
      ],
      "joint_positions": [
        -2.3557077283914496,
        -0.056581020823342223,
        1.888206889131095,
        -3.0718,
        -2.3400375460998144,
        3.216444049045192,
        2.272845410345471
      ],
      "pass_index": 0,
      "pass_seed": 201008,
      "sampled_yaw_rad": -0.3865678151646179,
      "target_point": {
        "x": 0.14219310504239474,
        "y": -0.004881379054485005,
        "z": 0.16140484062072843
      },
      "tip_link": "panda_link8"
    },
    {
      "attempt": 54,
      "attempt_global": 54,
      "index": 45,
      "joint_names": [
        "panda_joint1",
        "panda_joint2",
        "panda_joint3",
        "panda_joint4",
        "panda_joint5",
        "panda_joint6",
        "panda_joint7"
      ],
      "joint_positions": [
        0.7145379222025435,
        0.059134019780391074,
        -1.1619642543060398,
        -3.0609206898153993,
        -2.3813235950036855,
        3.22036782411169,
        2.3345189090515714
      ],
      "pass_index": 0,
      "pass_seed": 201008,
      "sampled_yaw_rad": -0.3865678151646179,
      "target_point": {
        "x": 0.14219310504239474,
        "y": -0.004881379054485005,
        "z": 0.16140484062072843
      },
      "tip_link": "panda_link8"
    },
    {
      "attempt": 55,
      "attempt_global": 55,
      "index": 46,
      "joint_names": [
        "panda_joint1",
        "panda_joint2",
        "panda_joint3",
        "panda_joint4",
        "panda_joint5",
        "panda_joint6",
        "panda_joint7"
      ],
      "joint_positions": [
        0.41435040919648447,
        0.07032392342416069,
        -0.7423135378774377,
        -3.007856181985569,
        -2.6149307945261477,
        3.2362297807939493,
        2.6885791993035326
      ],
      "pass_index": 0,
      "pass_seed": 201008,
      "sampled_yaw_rad": -0.3865678151646179,
      "target_point": {
        "x": 0.14219310504239474,
        "y": -0.004881379054485005,
        "z": 0.16140484062072843
      },
      "tip_link": "panda_link8"
    },
    {
      "attempt": 56,
      "attempt_global": 56,
      "index": 47,
      "joint_names": [
        "panda_joint1",
        "panda_joint2",
        "panda_joint3",
        "panda_joint4",
        "panda_joint5",
        "panda_joint6",
        "panda_joint7"
      ],
      "joint_positions": [
        0.738119623854021,
        0.058277659837563695,
        -1.1924780113334577,
        -3.0646123655270427,
        -2.3671411301459226,
        3.21906782326985,
        2.3133001854715176
      ],
      "pass_index": 0,
      "pass_seed": 201008,
      "sampled_yaw_rad": -0.3865678151646179,
      "target_point": {
        "x": 0.14219310504239474,
        "y": -0.004881379054485005,
        "z": 0.16140484062072843
      },
      "tip_link": "panda_link8"
    },
    {
      "attempt": 57,
      "attempt_global": 57,
      "index": 48,
      "joint_names": [
        "panda_joint1",
        "panda_joint2",
        "panda_joint3",
        "panda_joint4",
        "panda_joint5",
        "panda_joint6",
        "panda_joint7"
      ],
      "joint_positions": [
        2.897299980079347,
        -0.07730630783908081,
        -2.780237595820313,
        -2.9691402133255402,
        2.8748382284730254,
        3.245358460950481,
        -2.361699977171584
      ],
      "pass_index": 0,
      "pass_seed": 201008,
      "sampled_yaw_rad": -0.3865678151646179,
      "target_point": {
        "x": 0.14219310504239474,
        "y": -0.004881379054485005,
        "z": 0.16140484062072843
      },
      "tip_link": "panda_link8"
    },
    {
      "attempt": 58,
      "attempt_global": 58,
      "index": 49,
      "joint_names": [
        "panda_joint1",
        "panda_joint2",
        "panda_joint3",
        "panda_joint4",
        "panda_joint5",
        "panda_joint6",
        "panda_joint7"
      ],
      "joint_positions": [
        0.44914022234649986,
        0.06907541294038733,
        -0.7942633775452299,
        -3.014284283916705,
        -2.5824598047405005,
        3.2345439670296114,
        2.6389060255042582
      ],
      "pass_index": 0,
      "pass_seed": 201008,
      "sampled_yaw_rad": -0.3865678151646179,
      "target_point": {
        "x": 0.14219310504239474,
        "y": -0.004881379054485005,
        "z": 0.16140484062072843
      },
      "tip_link": "panda_link8"
    },
    {
      "attempt": 59,
      "attempt_global": 59,
      "index": 50,
      "joint_names": [
        "panda_joint1",
        "panda_joint2",
        "panda_joint3",
        "panda_joint4",
        "panda_joint5",
        "panda_joint6",
        "panda_joint7"
      ],
      "joint_positions": [
        -0.7101135039332729,
        0.06185011663890074,
        1.0653930443978266,
        -3.0489106329080182,
        2.428857675153618,
        3.2243946410688356,
        -0.879794617675011
      ],
      "pass_index": 0,
      "pass_seed": 201008,
      "sampled_yaw_rad": 0.41129221485338574,
      "target_point": {
        "x": 0.14219310504239474,
        "y": -0.004881379054485005,
        "z": 0.16140484062072843
      },
      "tip_link": "panda_link8"
    },
    {
      "attempt": 60,
      "attempt_global": 60,
      "index": 51,
      "joint_names": [
        "panda_joint1",
        "panda_joint2",
        "panda_joint3",
        "panda_joint4",
        "panda_joint5",
        "panda_joint6",
        "panda_joint7"
      ],
      "joint_positions": [
        -0.6604705982540641,
        0.06372710291106232,
        0.9978849027268349,
        -3.0403084108305993,
        2.4644135189724476,
        3.2271032063834832,
        -0.9334198312403825
      ],
      "pass_index": 0,
      "pass_seed": 201008,
      "sampled_yaw_rad": 0.41129221485338574,
      "target_point": {
        "x": 0.14219310504239474,
        "y": -0.004881379054485005,
        "z": 0.16140484062072843
      },
      "tip_link": "panda_link8"
    },
    {
      "attempt": 61,
      "attempt_global": 61,
      "index": 52,
      "joint_names": [
        "panda_joint1",
        "panda_joint2",
        "panda_joint3",
        "panda_joint4",
        "panda_joint5",
        "panda_joint6",
        "panda_joint7"
      ],
      "joint_positions": [
        -0.6402795249515574,
        0.06449292243256373,
        0.9699602497768449,
        -3.03672255686902,
        2.479664990327483,
        3.2281927466973612,
        -0.9564823550800124
      ],
      "pass_index": 0,
      "pass_seed": 201008,
      "sampled_yaw_rad": 0.41129221485338574,
      "target_point": {
        "x": 0.14219310504239474,
        "y": -0.004881379054485005,
        "z": 0.16140484062072843
      },
      "tip_link": "panda_link8"
    },
    {
      "attempt": 62,
      "attempt_global": 62,
      "index": 53,
      "joint_names": [
        "panda_joint1",
        "panda_joint2",
        "panda_joint3",
        "panda_joint4",
        "panda_joint5",
        "panda_joint6",
        "panda_joint7"
      ],
      "joint_positions": [
        -0.5170831901422547,
        0.06910003160406626,
        0.7932481303845109,
        -3.01415838152899,
        2.5830806297044404,
        3.2345774142226045,
        -1.1137617530254806
      ],
      "pass_index": 0,
      "pass_seed": 201008,
      "sampled_yaw_rad": 0.41129221485338574,
      "target_point": {
        "x": 0.14219310504239474,
        "y": -0.004881379054485005,
        "z": 0.16140484062072843
      },
      "tip_link": "panda_link8"
    },
    {
      "attempt": 63,
      "attempt_global": 63,
      "index": 54,
      "joint_names": [
        "panda_joint1",
        "panda_joint2",
        "panda_joint3",
        "panda_joint4",
        "panda_joint5",
        "panda_joint6",
        "panda_joint7"
      ],
      "joint_positions": [
        -0.8545226868994177,
        0.056580775198317085,
        1.2533938158904063,
        -3.0718,
        2.3400338239059053,
        3.216443681342429,
        -0.7467469704298546
      ],
      "pass_index": 0,
      "pass_seed": 201008,
      "sampled_yaw_rad": 0.41129221485338574,
      "target_point": {
        "x": 0.14219310504239474,
        "y": -0.004881379054485005,
        "z": 0.16140484062072843
      },
      "tip_link": "panda_link8"
    },
    {
      "attempt": 64,
      "attempt_global": 64,
      "index": 55,
      "joint_names": [
        "panda_joint1",
        "panda_joint2",
        "panda_joint3",
        "panda_joint4",
        "panda_joint5",
        "panda_joint6",
        "panda_joint7"
      ],
      "joint_positions": [
        -0.4059617370732726,
        0.07293065391357186,
        0.6239914975888005,
        -2.9939665512248745,
        2.6919180343903286,
        3.239694615340025,
        -1.2807415978851122
      ],
      "pass_index": 0,
      "pass_seed": 201008,
      "sampled_yaw_rad": 0.41129221485338574,
      "target_point": {
        "x": 0.14219310504239474,
        "y": -0.004881379054485005,
        "z": 0.16140484062072843
      },
      "tip_link": "panda_link8"
    },
    {
      "attempt": 65,
      "attempt_global": 65,
      "index": 56,
      "joint_names": [
        "panda_joint1",
        "panda_joint2",
        "panda_joint3",
        "panda_joint4",
        "panda_joint5",
        "panda_joint6",
        "panda_joint7"
      ],
      "joint_positions": [
        0.29388208460005766,
        0.07427436991778587,
        -0.5552291081339724,
        -2.9865360914683987,
        -2.738399670950121,
        3.2414563909526715,
        -2.6068049617917914
      ],
      "pass_index": 0,
      "pass_seed": 201008,
      "sampled_yaw_rad": 0.41129221485338574,
      "target_point": {
        "x": 0.14219310504239474,
        "y": -0.004881379054485005,
        "z": 0.16140484062072843
      },
      "tip_link": "panda_link8"
    },
    {
      "attempt": 66,
      "attempt_global": 66,
      "index": 57,
      "joint_names": [
        "panda_joint1",
        "panda_joint2",
        "panda_joint3",
        "panda_joint4",
        "panda_joint5",
        "panda_joint6",
        "panda_joint7"
      ],
      "joint_positions": [
        -0.4757510678054802,
        0.07057778791257396,
        0.7314089464767014,
        -3.006530886984324,
        2.62184247098658,
        3.2365704187889928,
        -1.1730763105201851
      ],
      "pass_index": 0,
      "pass_seed": 201008,
      "sampled_yaw_rad": 0.41129221485338574,
      "target_point": {
        "x": 0.14219310504239474,
        "y": -0.004881379054485005,
        "z": 0.16140484062072843
      },
      "tip_link": "panda_link8"
    },
    {
      "attempt": 67,
      "attempt_global": 67,
      "index": 58,
      "joint_names": [
        "panda_joint1",
        "panda_joint2",
        "panda_joint3",
        "panda_joint4",
        "panda_joint5",
        "panda_joint6",
        "panda_joint7"
      ],
      "joint_positions": [
        -0.3516852915084146,
        0.07459464680021215,
        0.5378722678510928,
        -2.9847551284751863,
        2.7503092057948417,
        3.241870116391209,
        -1.3708268083000914
      ],
      "pass_index": 0,
      "pass_seed": 201008,
      "sampled_yaw_rad": 0.41129221485338574,
      "target_point": {
        "x": 0.14219310504239474,
        "y": -0.004881379054485005,
        "z": 0.16140484062072843
      },
      "tip_link": "panda_link8"
    },
    {
      "attempt": 68,
      "attempt_global": 68,
      "index": 59,
      "joint_names": [
        "panda_joint1",
        "panda_joint2",
        "panda_joint3",
        "panda_joint4",
        "panda_joint5",
        "panda_joint6",
        "panda_joint7"
      ],
      "joint_positions": [
        -0.37347317822195475,
        0.07394689749445697,
        0.5727086528366909,
        -2.9883738783849956,
        2.7264728305467023,
        3.2410264596066463,
        -1.3340151578412054
      ],
      "pass_index": 0,
      "pass_seed": 201008,
      "sampled_yaw_rad": 0.41129221485338574,
      "target_point": {
        "x": 0.14219310504239474,
        "y": -0.004881379054485005,
        "z": 0.16140484062072843
      },
      "tip_link": "panda_link8"
    },
    {
      "attempt": 69,
      "attempt_global": 69,
      "index": 60,
      "joint_names": [
        "panda_joint1",
        "panda_joint2",
        "panda_joint3",
        "panda_joint4",
        "panda_joint5",
        "panda_joint6",
        "panda_joint7"
      ],
      "joint_positions": [
        -2.897299205907259,
        -0.07567138277605916,
        2.6665347637386243,
        -2.9786462299159147,
        -2.7939539830952147,
        3.2432638809437915,
        -1.9031611942382378
      ],
      "pass_index": 0,
      "pass_seed": 201008,
      "sampled_yaw_rad": 1.0290149011748815,
      "target_point": {
        "x": 0.14219310504239474,
        "y": -0.004881379054485005,
        "z": 0.16140484062072843
      },
      "tip_link": "panda_link8"
    },
    {
      "attempt": 71,
      "attempt_global": 71,
      "index": 61,
      "joint_names": [
        "panda_joint1",
        "panda_joint2",
        "panda_joint3",
        "panda_joint4",
        "panda_joint5",
        "panda_joint6",
        "panda_joint7"
      ],
      "joint_positions": [
        -2.6965442625466727,
        -0.06922356527635383,
        2.353386661542975,
        -3.0135283342070154,
        -2.586194526292255,
        3.2347449721037815,
        -2.2229897810987578
      ],
      "pass_index": 0,
      "pass_seed": 201008,
      "sampled_yaw_rad": 1.0290149011748815,
      "target_point": {
        "x": 0.14219310504239474,
        "y": -0.004881379054485005,
        "z": 0.16140484062072843
      },
      "tip_link": "panda_link8"
    },
    {
      "attempt": 72,
      "attempt_global": 72,
      "index": 62,
      "joint_names": [
        "panda_joint1",
        "panda_joint2",
        "panda_joint3",
        "panda_joint4",
        "panda_joint5",
        "panda_joint6",
        "panda_joint7"
      ],
      "joint_positions": [
        0.785889094164888,
        0.05658086675027241,
        -1.2533910329614348,
        -3.0718,
        -2.3400352700798743,
        3.2164438172616823,
        -2.59476057464641
      ],
      "pass_index": 0,
      "pass_seed": 201008,
      "sampled_yaw_rad": 1.0290149011748815,
      "target_point": {
        "x": 0.14219310504239474,
        "y": -0.004881379054485005,
        "z": 0.16140484062072843
      },
      "tip_link": "panda_link8"
    },
    {
      "attempt": 73,
      "attempt_global": 73,
      "index": 63,
      "joint_names": [
        "panda_joint1",
        "panda_joint2",
        "panda_joint3",
        "panda_joint4",
        "panda_joint5",
        "panda_joint6",
        "panda_joint7"
      ],
      "joint_positions": [
        -2.6283813720644855,
        -0.06670268859055703,
        2.2540690564839028,
        -3.02612211410923,
        -2.526477694460103,
        3.231289249860153,
        -2.314017665529542
      ],
      "pass_index": 0,
      "pass_seed": 201008,
      "sampled_yaw_rad": 1.0290149011748815,
      "target_point": {
        "x": 0.14219310504239474,
        "y": -0.004881379054485005,
        "z": 0.16140484062072843
      },
      "tip_link": "panda_link8"
    },
    {
      "attempt": 74,
      "attempt_global": 74,
      "index": 64,
      "joint_names": [
        "panda_joint1",
        "panda_joint2",
        "panda_joint3",
        "panda_joint4",
        "panda_joint5",
        "panda_joint6",
        "panda_joint7"
      ],
      "joint_positions": [
        -0.8545223943514505,
        0.056580802459046835,
        1.2533932967582386,
        -3.0718,
        2.340034331514429,
        3.216443722563627,
        -0.12902502040711789
      ],
      "pass_index": 0,
      "pass_seed": 201008,
      "sampled_yaw_rad": 1.0290149011748815,
      "target_point": {
        "x": 0.14219310504239474,
        "y": -0.004881379054485005,
        "z": 0.16140484062072843
      },
      "tip_link": "panda_link8"
    },
    {
      "attempt": 75,
      "attempt_global": 75,
      "index": 65,
      "joint_names": [
        "panda_joint1",
        "panda_joint2",
        "panda_joint3",
        "panda_joint4",
        "panda_joint5",
        "panda_joint6",
        "panda_joint7"
      ],
      "joint_positions": [
        -2.816097294605944,
        -0.07330663723080366,
        2.5361897577694323,
        -2.9919045106306172,
        -2.7043732826588966,
        3.2401905569949614,
        -2.041582282339756
      ],
      "pass_index": 0,
      "pass_seed": 201008,
      "sampled_yaw_rad": 1.0290149011748815,
      "target_point": {
        "x": 0.14219310504239474,
        "y": -0.004881379054485005,
        "z": 0.16140484062072843
      },
      "tip_link": "panda_link8"
    },
    {
      "attempt": 76,
      "attempt_global": 76,
      "index": 66,
      "joint_names": [
        "panda_joint1",
        "panda_joint2",
        "panda_joint3",
        "panda_joint4",
        "panda_joint5",
        "panda_joint6",
        "panda_joint7"
      ],
      "joint_positions": [
        2.8973,
        -0.07730630838052906,
        -2.7802376435234266,
        -2.9691402106823044,
        2.8748382525685043,
        3.245358460937314,
        -0.946117298099653
      ],
      "pass_index": 0,
      "pass_seed": 201008,
      "sampled_yaw_rad": 1.0290149011748815,
      "target_point": {
        "x": 0.14219310504239474,
        "y": -0.004881379054485005,
        "z": 0.16140484062072843
      },
      "tip_link": "panda_link8"
    },
    {
      "attempt": 78,
      "attempt_global": 78,
      "index": 67,
      "joint_names": [
        "panda_joint1",
        "panda_joint2",
        "panda_joint3",
        "panda_joint4",
        "panda_joint5",
        "panda_joint6",
        "panda_joint7"
      ],
      "joint_positions": [
        -2.6156042877687713,
        -0.06622194341758195,
        2.235836287954609,
        -3.028462548660471,
        -2.5159011012251793,
        3.2306211448760958,
        -2.330088912800117
      ],
      "pass_index": 0,
      "pass_seed": 201008,
      "sampled_yaw_rad": 1.0290149011748815,
      "target_point": {
        "x": 0.14219310504239474,
        "y": -0.004881379054485005,
        "z": 0.16140484062072843
      },
      "tip_link": "panda_link8"
    },
    {
      "attempt": 80,
      "attempt_global": 80,
      "index": 68,
      "joint_names": [
        "panda_joint1",
        "panda_joint2",
        "panda_joint3",
        "panda_joint4",
        "panda_joint5",
        "panda_joint6",
        "panda_joint7"
      ],
      "joint_positions": [
        2.498926921968839,
        -0.0644029444947104,
        -2.168320626787895,
        -3.037147889984933,
        2.477841922270706,
        3.2280649519063647,
        -0.3360021055521926
      ],
      "pass_index": 0,
      "pass_seed": 201008,
      "sampled_yaw_rad": 1.0290149011748815,
      "target_point": {
        "x": 0.14219310504239474,
        "y": -0.004881379054485005,
        "z": 0.16140484062072843
      },
      "tip_link": "panda_link8"
    },
    {
      "attempt": 81,
      "attempt_global": 81,
      "index": 69,
      "joint_names": [
        "panda_joint1",
        "panda_joint2",
        "panda_joint3",
        "panda_joint4",
        "panda_joint5",
        "panda_joint6",
        "panda_joint7"
      ],
      "joint_positions": [
        -2.656073326804598,
        -0.0677372501673803,
        2.2939973825807067,
        -3.0210199074151793,
        -2.550066763420251,
        3.232716920594533,
        -2.278117382311757
      ],
      "pass_index": 0,
      "pass_seed": 201008,
      "sampled_yaw_rad": 1.0290149011748815,
      "target_point": {
        "x": 0.14219310504239474,
        "y": -0.004881379054485005,
        "z": 0.16140484062072843
      },
      "tip_link": "panda_link8"
    },
    {
      "attempt": 82,
      "attempt_global": 82,
      "index": 70,
      "joint_names": [
        "panda_joint1",
        "panda_joint2",
        "panda_joint3",
        "panda_joint4",
        "panda_joint5",
        "panda_joint6",
        "panda_joint7"
      ],
      "joint_positions": [
        -2.355706930465899,
        -0.05658098393187769,
        1.8882058632182503,
        -3.0718,
        -2.3400370561572097,
        3.216443995869757,
        -2.086546746394294
      ],
      "pass_index": 0,
      "pass_seed": 201008,
      "sampled_yaw_rad": 1.537226057480635,
      "target_point": {
        "x": 0.14219310504239474,
        "y": -0.004881379054485005,
        "z": 0.16140484062072843
      },
      "tip_link": "panda_link8"
    },
    {
      "attempt": 83,
      "attempt_global": 83,
      "index": 71,
      "joint_names": [
        "panda_joint1",
        "panda_joint2",
        "panda_joint3",
        "panda_joint4",
        "panda_joint5",
        "panda_joint6",
        "panda_joint7"
      ],
      "joint_positions": [
        -0.2932700080475011,
        0.07617411162188861,
        0.4428110951640898,
        -2.9757361737306116,
        2.8166412243697514,
        3.2439171558425763,
        -0.3475812098870293
      ],
      "pass_index": 0,
      "pass_seed": 201008,
      "sampled_yaw_rad": 1.537226057480635,
      "target_point": {
        "x": 0.14219310504239474,
        "y": -0.004881379054485005,
        "z": 0.16140484062072843
      },
      "tip_link": "panda_link8"
    },
    {
      "attempt": 84,
      "attempt_global": 84,
      "index": 72,
      "joint_names": [
        "panda_joint1",
        "panda_joint2",
        "panda_joint3",
        "panda_joint4",
        "panda_joint5",
        "panda_joint6",
        "panda_joint7"
      ],
      "joint_positions": [
        -0.6897428725395952,
        0.0626182054200782,
        1.0378863105954563,
        -3.045420951726103,
        2.443115983834965,
        3.2255099181416065,
        0.2246591365790008
      ],
      "pass_index": 0,
      "pass_seed": 201008,
      "sampled_yaw_rad": 1.537226057480635,
      "target_point": {
        "x": 0.14219310504239474,
        "y": -0.004881379054485005,
        "z": 0.16140484062072843
      },
      "tip_link": "panda_link8"
    },
    {
      "attempt": 85,
      "attempt_global": 85,
      "index": 73,
      "joint_names": [
        "panda_joint1",
        "panda_joint2",
        "panda_joint3",
        "panda_joint4",
        "panda_joint5",
        "panda_joint6",
        "panda_joint7"
      ],
      "joint_positions": [
        0.3862773764638493,
        0.07130171163370694,
        -0.6997231600629709,
        -3.0027212232257163,
        -2.642168519115307,
        3.237537972411055,
        -1.629047679582779
      ],
      "pass_index": 0,
      "pass_seed": 201008,
      "sampled_yaw_rad": 1.537226057480635,
      "target_point": {
        "x": 0.14219310504239474,
        "y": -0.004881379054485005,
        "z": 0.16140484062072843
      },
      "tip_link": "panda_link8"
    },
    {
      "attempt": 86,
      "attempt_global": 86,
      "index": 74,
      "joint_names": [
        "panda_joint1",
        "panda_joint2",
        "panda_joint3",
        "panda_joint4",
        "panda_joint5",
        "panda_joint6",
        "panda_joint7"
      ],
      "joint_positions": [
        0.3826686444190096,
        0.07143278574597159,
        -0.6940869660043611,
        -3.002018528257642,
        -2.645915501945182,
        3.237727375437426,
        -1.6232723337018868
      ],
      "pass_index": 0,
      "pass_seed": 201008,
      "sampled_yaw_rad": 1.537226057480635,
      "target_point": {
        "x": 0.14219310504239474,
        "y": -0.004881379054485005,
        "z": 0.16140484062072843
      },
      "tip_link": "panda_link8"
    },
    {
      "attempt": 87,
      "attempt_global": 87,
      "index": 75,
      "joint_names": [
        "panda_joint1",
        "panda_joint2",
        "panda_joint3",
        "panda_joint4",
        "panda_joint5",
        "panda_joint6",
        "panda_joint7"
      ],
      "joint_positions": [
        -2.897298995196022,
        -0.07567170984113712,
        2.666532907225087,
        -2.9786463622334063,
        -2.793948661706846,
        3.2432636840670686,
        -1.3949569144230054
      ],
      "pass_index": 0,
      "pass_seed": 201008,
      "sampled_yaw_rad": 1.537226057480635,
      "target_point": {
        "x": 0.14219310504239474,
        "y": -0.004881379054485005,
        "z": 0.16140484062072843
      },
      "tip_link": "panda_link8"
    },
    {
      "attempt": 88,
      "attempt_global": 88,
      "index": 76,
      "joint_names": [
        "panda_joint1",
        "panda_joint2",
        "panda_joint3",
        "panda_joint4",
        "panda_joint5",
        "panda_joint6",
        "panda_joint7"
      ],
      "joint_positions": [
        -2.6682692500155802,
        -0.06818904629181179,
        2.3117657090300057,
        -3.0187633580066224,
        -2.5607504390438285,
        3.2333361775828173,
        -1.753621815918689
      ],
      "pass_index": 0,
      "pass_seed": 201008,
      "sampled_yaw_rad": 1.537226057480635,
      "target_point": {
        "x": 0.14219310504239474,
        "y": -0.004881379054485005,
        "z": 0.16140484062072843
      },
      "tip_link": "panda_link8"
    },
    {
      "attempt": 89,
      "attempt_global": 89,
      "index": 77,
      "joint_names": [
        "panda_joint1",
        "panda_joint2",
        "panda_joint3",
        "panda_joint4",
        "panda_joint5",
        "panda_joint6",
        "panda_joint7"
      ],
      "joint_positions": [
        2.8972999811271816,
        -0.07730630794469287,
        -2.7802375944939204,
        -2.9691402137416714,
        2.8748382235076972,
        3.245358460593583,
        -0.43790609720494716
      ],
      "pass_index": 0,
      "pass_seed": 201008,
      "sampled_yaw_rad": 1.537226057480635,
      "target_point": {
        "x": 0.14219310504239474,
        "y": -0.004881379054485005,
        "z": 0.16140484062072843
      },
      "tip_link": "panda_link8"
    },
    {
      "attempt": 90,
      "attempt_global": 90,
      "index": 78,
      "joint_names": [
        "panda_joint1",
        "panda_joint2",
        "panda_joint3",
        "panda_joint4",
        "panda_joint5",
        "panda_joint6",
        "panda_joint7"
      ],
      "joint_positions": [
        -2.649987568727531,
        -0.06751101058977375,
        2.285174730991295,
        -3.02214350143424,
        -2.5448062866668004,
        3.232405862784862,
        -1.7779188193075004
      ],
      "pass_index": 0,
      "pass_seed": 201008,
      "sampled_yaw_rad": 1.537226057480635,
      "target_point": {
        "x": 0.14219310504239474,
        "y": -0.004881379054485005,
        "z": 0.16140484062072843
      },
      "tip_link": "panda_link8"
    },
    {
      "attempt": 91,
      "attempt_global": 91,
      "index": 79,
      "joint_names": [
        "panda_joint1",
        "panda_joint2",
        "panda_joint3",
        "panda_joint4",
        "panda_joint5",
        "panda_joint6",
        "panda_joint7"
      ],
      "joint_positions": [
        -2.6554821533187454,
        -0.06771542778443564,
        2.2931403096743157,
        -3.021128602746649,
        -2.5495561486197182,
        3.2326869345318214,
        -1.7706841730951974
      ],
      "pass_index": 0,
      "pass_seed": 201008,
      "sampled_yaw_rad": 1.537226057480635,
      "target_point": {
        "x": 0.14219310504239474,
        "y": -0.004881379054485005,
        "z": 0.16140484062072843
      },
      "tip_link": "panda_link8"
    },
    {
      "attempt": 92,
      "attempt_global": 92,
      "index": 80,
      "joint_names": [
        "panda_joint1",
        "panda_joint2",
        "panda_joint3",
        "panda_joint4",
        "panda_joint5",
        "panda_joint6",
        "panda_joint7"
      ],
      "joint_positions": [
        0.785886119422444,
        0.05658097083918849,
        -1.2533872854310597,
        -3.0718,
        -2.340036854868086,
        3.216443975536501,
        -1.6449179945729875
      ],
      "pass_index": 0,
      "pass_seed": 201008,
      "sampled_yaw_rad": 1.978855111027804,
      "target_point": {
        "x": 0.14219310504239474,
        "y": -0.004881379054485005,
        "z": 0.16140484062072843
      },
      "tip_link": "panda_link8"
    },
    {
      "attempt": 93,
      "attempt_global": 93,
      "index": 81,
      "joint_names": [
        "panda_joint1",
        "panda_joint2",
        "panda_joint3",
        "panda_joint4",
        "panda_joint5",
        "panda_joint6",
        "panda_joint7"
      ],
      "joint_positions": [
        0.5580530973685973,
        0.06500918940388474,
        -0.9509953202185993,
        -3.034282345020683,
        -2.4902034115410903,
        3.2289220405379404,
        -1.4192288863275049
      ],
      "pass_index": 0,
      "pass_seed": 201008,
      "sampled_yaw_rad": 1.978855111027804,
      "target_point": {
        "x": 0.14219310504239474,
        "y": -0.004881379054485005,
        "z": 0.16140484062072843
      },
      "tip_link": "panda_link8"
    },
    {
      "attempt": 94,
      "attempt_global": 94,
      "index": 82,
      "joint_names": [
        "panda_joint1",
        "panda_joint2",
        "panda_joint3",
        "panda_joint4",
        "panda_joint5",
        "panda_joint6",
        "panda_joint7"
      ],
      "joint_positions": [
        0.5327128225172272,
        0.06596819131242779,
        -0.9153044388863996,
        -3.029689889860762,
        -2.5104122218218112,
        3.23026731672162,
        -1.3885827272408424
      ],
      "pass_index": 0,
      "pass_seed": 201008,
      "sampled_yaw_rad": 1.978855111027804,
      "target_point": {
        "x": 0.14219310504239474,
        "y": -0.004881379054485005,
        "z": 0.16140484062072843
      },
      "tip_link": "panda_link8"
    },
    {
      "attempt": 95,
      "attempt_global": 95,
      "index": 83,
      "joint_names": [
        "panda_joint1",
        "panda_joint2",
        "panda_joint3",
        "panda_joint4",
        "panda_joint5",
        "panda_joint6",
        "panda_joint7"
      ],
      "joint_positions": [
        0.5553735441944941,
        0.06512287966497854,
        -0.9471754639040985,
        -3.0337636913307677,
        -2.492430178629097,
        3.229082028158133,
        -1.415851252178167
      ],
      "pass_index": 0,
      "pass_seed": 201008,
      "sampled_yaw_rad": 1.978855111027804,
      "target_point": {
        "x": 0.14219310504239474,
        "y": -0.004881379054485005,
        "z": 0.16140484062072843
      },
      "tip_link": "panda_link8"
    },
    {
      "attempt": 96,
      "attempt_global": 96,
      "index": 84,
      "joint_names": [
        "panda_joint1",
        "panda_joint2",
        "panda_joint3",
        "panda_joint4",
        "panda_joint5",
        "panda_joint6",
        "panda_joint7"
      ],
      "joint_positions": [
        0.6810370727115446,
        0.06036735630704065,
        -1.1180833366406575,
        -3.055519879252286,
        -2.4024202695707872,
        3.2222146351245375,
        -1.551618973166569
      ],
      "pass_index": 0,
      "pass_seed": 201008,
      "sampled_yaw_rad": 1.978855111027804,
      "target_point": {
        "x": 0.14219310504239474,
        "y": -0.004881379054485005,
        "z": 0.16140484062072843
      },
      "tip_link": "panda_link8"
    },
    {
      "attempt": 98,
      "attempt_global": 98,
      "index": 85,
      "joint_names": [
        "panda_joint1",
        "panda_joint2",
        "panda_joint3",
        "panda_joint4",
        "panda_joint5",
        "panda_joint6",
        "panda_joint7"
      ],
      "joint_positions": [
        2.4270789152117414,
        -0.06168920881060268,
        -2.0703209261847086,
        -3.0496443064805714,
        2.4259089743310103,
        3.2241570593785114,
        0.6922136690799772
      ],
      "pass_index": 0,
      "pass_seed": 201008,
      "sampled_yaw_rad": 1.978855111027804,
      "target_point": {
        "x": 0.14219310504239474,
        "y": -0.004881379054485005,
        "z": 0.16140484062072843
      },
      "tip_link": "panda_link8"
    },
    {
      "attempt": 99,
      "attempt_global": 99,
      "index": 86,
      "joint_names": [
        "panda_joint1",
        "panda_joint2",
        "panda_joint3",
        "panda_joint4",
        "panda_joint5",
        "panda_joint6",
        "panda_joint7"
      ],
      "joint_positions": [
        0.6096082541025708,
        0.06305355205240393,
        -1.0222340824751313,
        -3.0434248084271363,
        -2.4513715025186156,
        3.226137707497414,
        -1.4779428442096898
      ],
      "pass_index": 0,
      "pass_seed": 201008,
      "sampled_yaw_rad": 1.978855111027804,
      "target_point": {
        "x": 0.14219310504239474,
        "y": -0.004881379054485005,
        "z": 0.16140484062072843
      },
      "tip_link": "panda_link8"
    },
    {
      "attempt": 100,
      "attempt_global": 100,
      "index": 87,
      "joint_names": [
        "panda_joint1",
        "panda_joint2",
        "panda_joint3",
        "panda_joint4",
        "panda_joint5",
        "panda_joint6",
        "panda_joint7"
      ],
      "joint_positions": [
        0.46637490698295825,
        0.06844505772952456,
        -0.8196541323712276,
        -3.0174767407750434,
        -2.566915907353459,
        3.2336859871335393,
        -1.3025882369204085
      ],
      "pass_index": 0,
      "pass_seed": 201008,
      "sampled_yaw_rad": 1.978855111027804,
      "target_point": {
        "x": 0.14219310504239474,
        "y": -0.004881379054485005,
        "z": 0.16140484062072843
      },
      "tip_link": "panda_link8"
    },
    {
      "attempt": 101,
      "attempt_global": 101,
      "index": 88,
      "joint_names": [
        "panda_joint1",
        "panda_joint2",
        "panda_joint3",
        "panda_joint4",
        "panda_joint5",
        "panda_joint6",
        "panda_joint7"
      ],
      "joint_positions": [
        0.5889537566427644,
        0.0638367311701152,
        -0.9939102385179688,
        -3.0397985057748467,
        -2.4665660003488328,
        3.2272596184593594,
        -1.4549965314204114
      ],
      "pass_index": 0,
      "pass_seed": 201008,
      "sampled_yaw_rad": 1.978855111027804,
      "target_point": {
        "x": 0.14219310504239474,
        "y": -0.004881379054485005,
        "z": 0.16140484062072843
      },
      "tip_link": "panda_link8"
    },
    {
      "attempt": 102,
      "attempt_global": 102,
      "index": 89,
      "joint_names": [
        "panda_joint1",
        "panda_joint2",
        "panda_joint3",
        "panda_joint4",
        "panda_joint5",
        "panda_joint6",
        "panda_joint7"
      ],
      "joint_positions": [
        0.3971545311830436,
        0.0709269943660128,
        -0.7162886038972088,
        -3.0047001081958307,
        -2.631521119882048,
        3.237037867090407,
        -1.2037551526934704
      ],
      "pass_index": 0,
      "pass_seed": 201008,
      "sampled_yaw_rad": 1.978855111027804,
      "target_point": {
        "x": 0.14219310504239474,
        "y": -0.004881379054485005,
        "z": 0.16140484062072843
      },
      "tip_link": "panda_link8"
    },
    {
      "attempt": 103,
      "attempt_global": 103,
      "index": 90,
      "joint_names": [
        "panda_joint1",
        "panda_joint2",
        "panda_joint3",
        "panda_joint4",
        "panda_joint5",
        "panda_joint6",
        "panda_joint7"
      ],
      "joint_positions": [
        2.794533519877268,
        -0.07472810932879578,
        -2.6111527617676162,
        -2.984005147282276,
        2.755419548290659,
        3.2420432533652668,
        0.8274979234943481
      ],
      "pass_index": 0,
      "pass_seed": 201008,
      "sampled_yaw_rad": 2.617515566943573,
      "target_point": {
        "x": 0.14219310504239474,
        "y": -0.004881379054485005,
        "z": 0.16140484062072843
      },
      "tip_link": "panda_link8"
    },
    {
      "attempt": 104,
      "attempt_global": 104,
      "index": 91,
      "joint_names": [
        "panda_joint1",
        "panda_joint2",
        "panda_joint3",
        "panda_joint4",
        "panda_joint5",
        "panda_joint6",
        "panda_joint7"
      ],
      "joint_positions": [
        2.7758945578585856,
        -0.07418108552273046,
        -2.581268843654163,
        -2.9870709237812294,
        2.734907288132812,
        3.241331836138506,
        0.8591879755221721
      ],
      "pass_index": 0,
      "pass_seed": 201008,
      "sampled_yaw_rad": 2.617515566943573,
      "target_point": {
        "x": 0.14219310504239474,
        "y": -0.004881379054485005,
        "z": 0.16140484062072843
      },
      "tip_link": "panda_link8"
    },
    {
      "attempt": 105,
      "attempt_global": 105,
      "index": 92,
      "joint_names": [
        "panda_joint1",
        "panda_joint2",
        "panda_joint3",
        "panda_joint4",
        "panda_joint5",
        "panda_joint6",
        "panda_joint7"
      ],
      "joint_positions": [
        2.451181211781151,
        -0.06259305576779627,
        -2.1027992500270734,
        -3.045536354252439,
        2.442641159506381,
        3.2254734282169415,
        1.3056647569854487
      ],
      "pass_index": 0,
      "pass_seed": 201008,
      "sampled_yaw_rad": 2.617515566943573,
      "target_point": {
        "x": 0.14219310504239474,
        "y": -0.004881379054485005,
        "z": 0.16140484062072843
      },
      "tip_link": "panda_link8"
    },
    {
      "attempt": 106,
      "attempt_global": 106,
      "index": 93,
      "joint_names": [
        "panda_joint1",
        "panda_joint2",
        "panda_joint3",
        "panda_joint4",
        "panda_joint5",
        "panda_joint6",
        "panda_joint7"
      ],
      "joint_positions": [
        2.5679715635789937,
        -0.06701096160326461,
        -2.2658643859123773,
        -3.0246110615878345,
        2.5333855875593794,
        3.2317161038643305,
        1.1682261436305823
      ],
      "pass_index": 0,
      "pass_seed": 201008,
      "sampled_yaw_rad": 2.617515566943573,
      "target_point": {
        "x": 0.14219310504239474,
        "y": -0.004881379054485005,
        "z": 0.16140484062072843
      },
      "tip_link": "panda_link8"
    },
    {
      "attempt": 107,
      "attempt_global": 107,
      "index": 94,
      "joint_names": [
        "panda_joint1",
        "panda_joint2",
        "panda_joint3",
        "panda_joint4",
        "panda_joint5",
        "panda_joint6",
        "panda_joint7"
      ],
      "joint_positions": [
        2.854836291324715,
        -0.07633783246459196,
        -2.709528230966732,
        -2.9748035308169567,
        2.8242714910033713,
        3.244121058183415,
        0.720886604495425
      ],
      "pass_index": 0,
      "pass_seed": 201008,
      "sampled_yaw_rad": 2.617515566943573,
      "target_point": {
        "x": 0.14219310504239474,
        "y": -0.004881379054485005,
        "z": 0.16140484062072843
      },
      "tip_link": "panda_link8"
    },
    {
      "attempt": 108,
      "attempt_global": 108,
      "index": 95,
      "joint_names": [
        "panda_joint1",
        "panda_joint2",
        "panda_joint3",
        "panda_joint4",
        "panda_joint5",
        "panda_joint6",
        "panda_joint7"
      ],
      "joint_positions": [
        2.869959926804507,
        -0.07669887584910881,
        -2.734584205477026,
        -2.9726997239281725,
        2.8421008054320565,
        3.244584801007314,
        0.6932268669183086
      ],
      "pass_index": 0,
      "pass_seed": 201008,
      "sampled_yaw_rad": 2.617515566943573,
      "target_point": {
        "x": 0.14219310504239474,
        "y": -0.004881379054485005,
        "z": 0.16140484062072843
      },
      "tip_link": "panda_link8"
    },
    {
      "attempt": 109,
      "attempt_global": 109,
      "index": 96,
      "joint_names": [
        "panda_joint1",
        "panda_joint2",
        "panda_joint3",
        "panda_joint4",
        "panda_joint5",
        "panda_joint6",
        "panda_joint7"
      ],
      "joint_positions": [
        2.7755393033998237,
        -0.07417045294536656,
        -2.5807017490080173,
        -2.9871302138019518,
        2.7345200133549894,
        3.2413179798598755,
        0.8597859429376186
      ],
      "pass_index": 0,
      "pass_seed": 201008,
      "sampled_yaw_rad": 2.617515566943573,
      "target_point": {
        "x": 0.14219310504239474,
        "y": -0.004881379054485005,
        "z": 0.16140484062072843
      },
      "tip_link": "panda_link8"
    },
    {
      "attempt": 110,
      "attempt_global": 110,
      "index": 97,
      "joint_names": [
        "panda_joint1",
        "panda_joint2",
        "panda_joint3",
        "panda_joint4",
        "panda_joint5",
        "panda_joint6",
        "panda_joint7"
      ],
      "joint_positions": [
        2.89096142727909,
        -0.07716866888340448,
        -2.769615422172932,
        -2.9699356220404156,
        2.8672061381507343,
        3.245188468120056,
        0.6542487269981699
      ],
      "pass_index": 0,
      "pass_seed": 201008,
      "sampled_yaw_rad": 2.617515566943573,
      "target_point": {
        "x": 0.14219310504239474,
        "y": -0.004881379054485005,
        "z": 0.16140484062072843
      },
      "tip_link": "panda_link8"
    },
    {
      "attempt": 111,
      "attempt_global": 111,
      "index": 98,
      "joint_names": [
        "panda_joint1",
        "panda_joint2",
        "panda_joint3",
        "panda_joint4",
        "panda_joint5",
        "panda_joint6",
        "panda_joint7"
      ],
      "joint_positions": [
        2.64395087760884,
        -0.06979704227963411,
        -2.377274702691709,
        -3.0105506586938358,
        2.6011489939524535,
        3.235534716395705,
        1.064879057073632
      ],
      "pass_index": 0,
      "pass_seed": 201008,
      "sampled_yaw_rad": 2.617515566943573,
      "target_point": {
        "x": 0.14219310504239474,
        "y": -0.004881379054485005,
        "z": 0.16140484062072843
      },
      "tip_link": "panda_link8"
    },
    {
      "attempt": 112,
      "attempt_global": 112,
      "index": 99,
      "joint_names": [
        "panda_joint1",
        "panda_joint2",
        "panda_joint3",
        "panda_joint4",
        "panda_joint5",
        "panda_joint6",
        "panda_joint7"
      ],
      "joint_positions": [
        2.2870932916276434,
        -0.05658167940575763,
        -1.8882298996058198,
        -3.0717968149395065,
        2.3400499227116534,
        3.216445299588685,
        1.4594524153645516
      ],
      "pass_index": 0,
      "pass_seed": 201008,
      "sampled_yaw_rad": 2.617515566943573,
      "target_point": {
        "x": 0.14219310504239474,
        "y": -0.004881379054485005,
        "z": 0.16140484062072843
      },
      "tip_link": "panda_link8"
    }
  ]
}