{
  "meta": {
    "accepted_with_shortfall": false,
    "attempts_total": 106,
    "elapsed_total_s": 0.1123504638671875,
    "found": 100,
    "group": "panda_arm",
    "ik_successes_total": 106,
    "ik_timeout_s": 0.1,
    "named_start_for_seeding": "ready",
    "nullspace_jitter": 0.02,
    "nullspace_step": 0.2,
    "num_spaces": 10,
    "pass_metas": [
      {
        "attempts": 106,
        "elapsed_s": 0.11204934120178223,
        "found": 100,
        "group": "panda_arm",
        "ik_successes": 106,
        "ik_timeout_s": 0.1,
        "named_start_for_seeding": "ready",
        "nullspace_jitter": 0.02,
        "nullspace_step": 0.2,
        "num_spaces": 10,
        "pass_index": 0,
        "requested": 100,
        "rng": {
          "deterministic_joint_seeds": true,
          "engine": "numpy.default_rng",
          "note": "Avoid MoveIt internal RNG (RobotState.set_to_random_positions)."
        },
        "seed": 401010,
        "seed_pass": 401010,
        "target_point": {
          "x": 0.38737102301538456,
          "y": -0.36265675272233033,
          "z": 0.5821005223025626
        },
        "tip_link": "panda_link8",
        "uniq_resolution_rad": 0.001,
        "yaw_range_rad": 6.283185307179586
      }
    ],
    "pass_seed_stride": 100000,
    "passes_requested": 3,
    "passes_used": 1,
    "precheck_attempts": 50,
    "precheck_found": 50,
    "precheck_ik_successes": 50,
    "precheck_max_attempts": 1200,
    "precheck_num_spaces": 8,
    "reason": "ok",
    "requested": 100,
    "resample_max": 200,
    "resample_trial_final": 1,
    "resample_trials_used": 1,
    "seed": 401010,
    "shortfall": 0,
    "target_point": {
      "x": 0.38737102301538456,
      "y": -0.36265675272233033,
      "z": 0.5821005223025626
    },
    "tip_link": "panda_link8",
    "uniq_resolution_rad": 0.001,
    "yaw_range_rad": 6.283185307179586
  },
  "solutions": [
    {
      "attempt": 1,
      "attempt_global": 1,
      "index": 0,
      "joint_names": [
        "panda_joint1",
        "panda_joint2",
        "panda_joint3",
        "panda_joint4",
        "panda_joint5",
        "panda_joint6",
        "panda_joint7"
      ],
      "joint_positions": [
        -2.1008322355297864,
        -0.3104938407557389,
        1.1722956348057452,
        -1.7854565543537362,
        0.2865665831453021,
        1.6579007078412915,
        -2.897159885369928
      ],
      "pass_index": 0,
      "pass_seed": 401010,
      "sampled_yaw_rad": -2.710170610293651,
      "target_point": {
        "x": 0.38737102301538456,
        "y": -0.36265675272233033,
        "z": 0.5821005223025626
      },
      "tip_link": "panda_link8"
    },
    {
      "attempt": 2,
      "attempt_global": 2,
      "index": 1,
      "joint_names": [
        "panda_joint1",
        "panda_joint2",
        "panda_joint3",
        "panda_joint4",
        "panda_joint5",
        "panda_joint6",
        "panda_joint7"
      ],
      "joint_positions": [
        0.36434096289495577,
        1.2714913952958244,
        -2.1610472702346293,
        -1.6861009848018376,
        1.15125217728581,
        1.053685330208888,
        2.8321466682194814
      ],
      "pass_index": 0,
      "pass_seed": 401010,
      "sampled_yaw_rad": -2.710170610293651,
      "target_point": {
        "x": 0.38737102301538456,
        "y": -0.36265675272233033,
        "z": 0.5821005223025626
      },
      "tip_link": "panda_link8"
    },
    {
      "attempt": 3,
      "attempt_global": 3,
      "index": 2,
      "joint_names": [
        "panda_joint1",
        "panda_joint2",
        "panda_joint3",
        "panda_joint4",
        "panda_joint5",
        "panda_joint6",
        "panda_joint7"
      ],
      "joint_positions": [
        1.6970483470236566,
        -1.6854635949655672,
        -0.5593331880521845,
        -1.6603274637008225,
        -1.6440228231454241,
        0.5568949742149188,
        -1.813614588001309
      ],
      "pass_index": 0,
      "pass_seed": 401010,
      "sampled_yaw_rad": -2.710170610293651,
      "target_point": {
        "x": 0.38737102301538456,
        "y": -0.36265675272233033,
        "z": 0.5821005223025626
      },
      "tip_link": "panda_link8"
    },
    {
      "attempt": 4,
      "attempt_global": 4,
      "index": 3,
      "joint_names": [
        "panda_joint1",
        "panda_joint2",
        "panda_joint3",
        "panda_joint4",
        "panda_joint5",
        "panda_joint6",
        "panda_joint7"
      ],
      "joint_positions": [
        -2.67254951693884,
        -1.116967071126216,
        1.0717007617911019,
        -1.7030987294945585,
        1.0139154590782204,
        1.1933055952459335,
        2.8973
      ],
      "pass_index": 0,
      "pass_seed": 401010,
      "sampled_yaw_rad": -2.710170610293651,
      "target_point": {
        "x": 0.38737102301538456,
        "y": -0.36265675272233033,
        "z": 0.5821005223025626
      },
      "tip_link": "panda_link8"
    },
    {
      "attempt": 5,
      "attempt_global": 5,
      "index": 4,
      "joint_names": [
        "panda_joint1",
        "panda_joint2",
        "panda_joint3",
        "panda_joint4",
        "panda_joint5",
        "panda_joint6",
        "panda_joint7"
      ],
      "joint_positions": [
        -1.81787586555128,
        -0.184714737904876,
        0.9731135439763642,
        -1.791857658571185,
        0.15343605561550952,
        1.6857454952314979,
        -2.7956751563017606
      ],
      "pass_index": 0,
      "pass_seed": 401010,
      "sampled_yaw_rad": -2.710170610293651,
      "target_point": {
        "x": 0.38737102301538456,
        "y": -0.36265675272233033,
        "z": 0.5821005223025626
      },
      "tip_link": "panda_link8"
    },
    {
      "attempt": 6,
      "attempt_global": 6,
      "index": 5,
      "joint_names": [
        "panda_joint1",
        "panda_joint2",
        "panda_joint3",
        "panda_joint4",
        "panda_joint5",
        "panda_joint6",
        "panda_joint7"
      ],
      "joint_positions": [
        1.8277466174636476,
        0.11395047199808775,
        -2.614638508614204,
        -1.7940987921978488,
        0.057660073807321056,
        1.6952936762777702,
        -2.722053973762187
      ],
      "pass_index": 0,
      "pass_seed": 401010,
      "sampled_yaw_rad": -2.710170610293651,
      "target_point": {
        "x": 0.38737102301538456,
        "y": -0.36265675272233033,
        "z": 0.5821005223025626
      },
      "tip_link": "panda_link8"
    },
    {
      "attempt": 7,
      "attempt_global": 7,
      "index": 6,
      "joint_names": [
        "panda_joint1",
        "panda_joint2",
        "panda_joint3",
        "panda_joint4",
        "panda_joint5",
        "panda_joint6",
        "panda_joint7"
      ],
      "joint_positions": [
        -1.8898666077571673,
        -0.20625808110513277,
        1.0302431128714427,
        -1.7909764231738452,
        0.17762291758496368,
        1.681957671078484,
        -2.8142053333716506
      ],
      "pass_index": 0,
      "pass_seed": 401010,
      "sampled_yaw_rad": -2.710170610293651,
      "target_point": {
        "x": 0.38737102301538456,
        "y": -0.36265675272233033,
        "z": 0.5821005223025626
      },
      "tip_link": "panda_link8"
    },
    {
      "attempt": 8,
      "attempt_global": 8,
      "index": 7,
      "joint_names": [
        "panda_joint1",
        "panda_joint2",
        "panda_joint3",
        "panda_joint4",
        "panda_joint5",
        "panda_joint6",
        "panda_joint7"
      ],
      "joint_positions": [
        -1.9706315984982734,
        -0.2373997159842744,
        1.0901168918627275,
        -1.789537951081778,
        0.21124769161714252,
        1.6757540934911597,
        -2.8399058076377566
      ],
      "pass_index": 0,
      "pass_seed": 401010,
      "sampled_yaw_rad": -2.710170610293651,
      "target_point": {
        "x": 0.38737102301538456,
        "y": -0.36265675272233033,
        "z": 0.5821005223025626
      },
      "tip_link": "panda_link8"
    },
    {
      "attempt": 9,
      "attempt_global": 9,
      "index": 8,
      "joint_names": [
        "panda_joint1",
        "panda_joint2",
        "panda_joint3",
        "panda_joint4",
        "panda_joint5",
        "panda_joint6",
        "panda_joint7"
      ],
      "joint_positions": [
        1.0405190690124355,
        0.3106633206632775,
        -1.9691666554159033,
        -1.7854459346797296,
        0.28673714695343483,
        1.6578539505144854,
        -2.897288947948993
      ],
      "pass_index": 0,
      "pass_seed": 401010,
      "sampled_yaw_rad": -2.710170610293651,
      "target_point": {
        "x": 0.38737102301538456,
        "y": -0.36265675272233033,
        "z": 0.5821005223025626
      },
      "tip_link": "panda_link8"
    },
    {
      "attempt": 10,
      "attempt_global": 10,
      "index": 9,
      "joint_names": [
        "panda_joint1",
        "panda_joint2",
        "panda_joint3",
        "panda_joint4",
        "panda_joint5",
        "panda_joint6",
        "panda_joint7"
      ],
      "joint_positions": [
        1.3326133936913995,
        0.1823800910910997,
        -2.175734371554354,
        -1.7919478503775232,
        0.15075229932399764,
        1.6861316859615423,
        -2.793617192701183
      ],
      "pass_index": 0,
      "pass_seed": 401010,
      "sampled_yaw_rad": -2.710170610293651,
      "target_point": {
        "x": 0.38737102301538456,
        "y": -0.36265675272233033,
        "z": 0.5821005223025626
      },
      "tip_link": "panda_link8"
    },
    {
      "attempt": 11,
      "attempt_global": 11,
      "index": 10,
      "joint_names": [
        "panda_joint1",
        "panda_joint2",
        "panda_joint3",
        "panda_joint4",
        "panda_joint5",
        "panda_joint6",
        "panda_joint7"
      ],
      "joint_positions": [
        -0.9612338082417198,
        -0.09963899005897178,
        0.19706332844306018,
        -1.7944259224135413,
        0.0196326886282939,
        1.696678985504605,
        -2.1210975931094893
      ],
      "pass_index": 0,
      "pass_seed": 401010,
      "sampled_yaw_rad": -2.138509431278541,
      "target_point": {
        "x": 0.38737102301538456,
        "y": -0.36265675272233033,
        "z": 0.5821005223025626
      },
      "tip_link": "panda_link8"
    },
    {
      "attempt": 12,
      "attempt_global": 12,
      "index": 11,
      "joint_names": [
        "panda_joint1",
        "panda_joint2",
        "panda_joint3",
        "panda_joint4",
        "panda_joint5",
        "panda_joint6",
        "panda_joint7"
      ],
      "joint_positions": [
        -0.5029078288111166,
        -0.10053029220439212,
        -0.2354702944324921,
        -1.7944068090328633,
        -0.023602964215101083,
        1.696598102002719,
        -2.0877798228510946
      ],
      "pass_index": 0,
      "pass_seed": 401010,
      "sampled_yaw_rad": -2.138509431278541,
      "target_point": {
        "x": 0.38737102301538456,
        "y": -0.36265675272233033,
        "z": 0.5821005223025626
      },
      "tip_link": "panda_link8"
    },
    {
      "attempt": 13,
      "attempt_global": 13,
      "index": 12,
      "joint_names": [
        "panda_joint1",
        "panda_joint2",
        "panda_joint3",
        "panda_joint4",
        "panda_joint5",
        "panda_joint6",
        "panda_joint7"
      ],
      "joint_positions": [
        -1.5084098574107363,
        -0.1307003267462459,
        0.7049993238017903,
        -1.793661457460148,
        0.08519943533773877,
        1.693438306035958,
        -2.1715923509912276
      ],
      "pass_index": 0,
      "pass_seed": 401010,
      "sampled_yaw_rad": -2.138509431278541,
      "target_point": {
        "x": 0.38737102301538456,
        "y": -0.36265675272233033,
        "z": 0.5821005223025626
      },
      "tip_link": "panda_link8"
    },
    {
      "attempt": 14,
      "attempt_global": 14,
      "index": 13,
      "joint_names": [
        "panda_joint1",
        "panda_joint2",
        "panda_joint3",
        "panda_joint4",
        "panda_joint5",
        "panda_joint6",
        "panda_joint7"
      ],
      "joint_positions": [
        -1.1510949147528713,
        -0.10535066247724269,
        0.3754382394739034,
        -1.794305099849982,
        0.03887311718934849,
        1.6961504268684058,
        -2.13592236701718
      ],
      "pass_index": 0,
      "pass_seed": 401010,
      "sampled_yaw_rad": -2.138509431278541,
      "target_point": {
        "x": 0.38737102301538456,
        "y": -0.36265675272233033,
        "z": 0.5821005223025626
      },
      "tip_link": "panda_link8"
    },
    {
      "attempt": 15,
      "attempt_global": 15,
      "index": 14,
      "joint_names": [
        "panda_joint1",
        "panda_joint2",
        "panda_joint3",
        "panda_joint4",
        "panda_joint5",
        "panda_joint6",
        "panda_joint7"
      ],
      "joint_positions": [
        -1.5356733241501541,
        -0.1338130540381425,
        0.7295475416567843,
        -1.7935737786414732,
        0.08971396968376236,
        1.6930657808024177,
        -2.175065760224781
      ],
      "pass_index": 0,
      "pass_seed": 401010,
      "sampled_yaw_rad": -2.138509431278541,
      "target_point": {
        "x": 0.38737102301538456,
        "y": -0.36265675272233033,
        "z": 0.5821005223025626
      },
      "tip_link": "panda_link8"
    },
    {
      "attempt": 16,
      "attempt_global": 16,
      "index": 15,
      "joint_names": [
        "panda_joint1",
        "panda_joint2",
        "panda_joint3",
        "panda_joint4",
        "panda_joint5",
        "panda_joint6",
        "panda_joint7"
      ],
      "joint_positions": [
        -1.0229880991083766,
        -0.1010565111369759,
        0.2552123006691016,
        -1.7943954889784004,
        0.025673932564102005,
        1.6965500300510488,
        -2.125752681123833
      ],
      "pass_index": 0,
      "pass_seed": 401010,
      "sampled_yaw_rad": -2.138509431278541,
      "target_point": {
        "x": 0.38737102301538456,
        "y": -0.36265675272233033,
        "z": 0.5821005223025626
      },
      "tip_link": "panda_link8"
    },
    {
      "attempt": 17,
      "attempt_global": 17,
      "index": 16,
      "joint_names": [
        "panda_joint1",
        "panda_joint2",
        "panda_joint3",
        "panda_joint4",
        "panda_joint5",
        "panda_joint6",
        "panda_joint7"
      ],
      "joint_positions": [
        -1.6258500107244291,
        -0.1459015146751744,
        0.8097586431852547,
        -1.7932144212486478,
        0.10624773276889388,
        1.6915369000364473,
        -2.1877812216601606
      ],
      "pass_index": 0,
      "pass_seed": 401010,
      "sampled_yaw_rad": -2.138509431278541,
      "target_point": {
        "x": 0.38737102301538456,
        "y": -0.36265675272233033,
        "z": 0.5821005223025626
      },
      "tip_link": "panda_link8"
    },
    {
      "attempt": 18,
      "attempt_global": 18,
      "index": 17,
      "joint_names": [
        "panda_joint1",
        "panda_joint2",
        "panda_joint3",
        "panda_joint4",
        "panda_joint5",
        "panda_joint6",
        "panda_joint7"
      ],
      "joint_positions": [
        -0.9718788912588066,
        -0.09984948176978278,
        0.2070950769557414,
        -1.7944214278170552,
        0.020660566078161486,
        1.6966599679118637,
        -2.1218896466149197
      ],
      "pass_index": 0,
      "pass_seed": 401010,
      "sampled_yaw_rad": -2.138509431278541,
      "target_point": {
        "x": 0.38737102301538456,
        "y": -0.36265675272233033,
        "z": 0.5821005223025626
      },
      "tip_link": "panda_link8"
    },
    {
      "attempt": 19,
      "attempt_global": 19,
      "index": 18,
      "joint_names": [
        "panda_joint1",
        "panda_joint2",
        "panda_joint3",
        "panda_joint4",
        "panda_joint5",
        "panda_joint6",
        "panda_joint7"
      ],
      "joint_positions": [
        -1.5057232746724836,
        -0.1304056369898312,
        0.7025738057807354,
        -1.7936696546433946,
        0.0847651708509044,
        1.693473124212209,
        -2.171258204471861
      ],
      "pass_index": 0,
      "pass_seed": 401010,
      "sampled_yaw_rad": -2.138509431278541,
      "target_point": {
        "x": 0.38737102301538456,
        "y": -0.36265675272233033,
        "z": 0.5821005223025626
      },
      "tip_link": "panda_link8"
    },
    {
      "attempt": 20,
      "attempt_global": 20,
      "index": 19,
      "joint_names": [
        "panda_joint1",
        "panda_joint2",
        "panda_joint3",
        "panda_joint4",
        "panda_joint5",
        "panda_joint6",
        "panda_joint7"
      ],
      "joint_positions": [
        -0.836241065357874,
        -0.0979313617994033,
        0.07913500935833623,
        -1.7944628740009547,
        0.007791192504407926,
        1.696832295075716,
        -2.111972580490373
      ],
      "pass_index": 0,
      "pass_seed": 401010,
      "sampled_yaw_rad": -2.138509431278541,
      "target_point": {
        "x": 0.38737102301538456,
        "y": -0.36265675272233033,
        "z": 0.5821005223025626
      },
      "tip_link": "panda_link8"
    },
    {
      "attempt": 21,
      "attempt_global": 21,
      "index": 20,
      "joint_names": [
        "panda_joint1",
        "panda_joint2",
        "panda_joint3",
        "panda_joint4",
        "panda_joint5",
        "panda_joint6",
        "panda_joint7"
      ],
      "joint_positions": [
        -0.054589050721150785,
        1.6818037069814828,
        -2.576365802739926,
        -1.6601695749764254,
        1.6372552343337308,
        0.562719583492333,
        -2.1399725714802322
      ],
      "pass_index": 0,
      "pass_seed": 401010,
      "sampled_yaw_rad": -1.3079686152925298,
      "target_point": {
        "x": 0.38737102301538456,
        "y": -0.36265675272233033,
        "z": 0.5821005223025626
      },
      "tip_link": "panda_link8"
    },
    {
      "attempt": 22,
      "attempt_global": 22,
      "index": 21,
      "joint_names": [
        "panda_joint1",
        "panda_joint2",
        "panda_joint3",
        "panda_joint4",
        "panda_joint5",
        "panda_joint6",
        "panda_joint7"
      ],
      "joint_positions": [
        0.23245538338977456,
        1.435158676874882,
        -2.2866528994690145,
        -1.670373427293562,
        1.3104062733737292,
        0.8846336063353374,
        -2.1051615234817707
      ],
      "pass_index": 0,
      "pass_seed": 401010,
      "sampled_yaw_rad": -1.3079686152925298,
      "target_point": {
        "x": 0.38737102301538456,
        "y": -0.36265675272233033,
        "z": 0.5821005223025626
      },
      "tip_link": "panda_link8"
    },
    {
      "attempt": 23,
      "attempt_global": 23,
      "index": 22,
      "joint_names": [
        "panda_joint1",
        "panda_joint2",
        "panda_joint3",
        "panda_joint4",
        "panda_joint5",
        "panda_joint6",
        "panda_joint7"
      ],
      "joint_positions": [
        -0.1046841406446594,
        1.7120340390726727,
        -2.6273341850285505,
        -1.662068435749119,
        1.69665452390793,
        0.5130907972251552,
        -2.133591067831142
      ],
      "pass_index": 0,
      "pass_seed": 401010,
      "sampled_yaw_rad": -1.3079686152925298,
      "target_point": {
        "x": 0.38737102301538456,
        "y": -0.36265675272233033,
        "z": 0.5821005223025626
      },
      "tip_link": "panda_link8"
    },
    {
      "attempt": 24,
      "attempt_global": 24,
      "index": 23,
      "joint_names": [
        "panda_joint1",
        "panda_joint2",
        "panda_joint3",
        "panda_joint4",
        "panda_joint5",
        "panda_joint6",
        "panda_joint7"
      ],
      "joint_positions": [
        -0.01893045531210684,
        1.6582258946635275,
        -2.540011012403093,
        -1.6595366067998132,
        1.5959579477071149,
        0.5991777977019414,
        -2.1420978328141786
      ],
      "pass_index": 0,
      "pass_seed": 401010,
      "sampled_yaw_rad": -1.3079686152925298,
      "target_point": {
        "x": 0.38737102301538456,
        "y": -0.36265675272233033,
        "z": 0.5821005223025626
      },
      "tip_link": "panda_link8"
    },
    {
      "attempt": 25,
      "attempt_global": 25,
      "index": 24,
      "joint_names": [
        "panda_joint1",
        "panda_joint2",
        "panda_joint3",
        "panda_joint4",
        "panda_joint5",
        "panda_joint6",
        "panda_joint7"
      ],
      "joint_positions": [
        0.30833497543092137,
        1.3452548575629137,
        -2.2132977556539895,
        -1.678604632653079,
        1.2204158347467797,
        0.9805441987788212,
        -2.07609428586709
      ],
      "pass_index": 0,
      "pass_seed": 401010,
      "sampled_yaw_rad": -1.3079686152925298,
      "target_point": {
        "x": 0.38737102301538456,
        "y": -0.36265675272233033,
        "z": 0.5821005223025626
      },
      "tip_link": "panda_link8"
    },
    {
      "attempt": 26,
      "attempt_global": 26,
      "index": 25,
      "joint_names": [
        "panda_joint1",
        "panda_joint2",
        "panda_joint3",
        "panda_joint4",
        "panda_joint5",
        "panda_joint6",
        "panda_joint7"
      ],
      "joint_positions": [
        -0.2039073009190691,
        1.7627745024473138,
        -2.7273570995096614,
        -1.6696052042101077,
        1.8216052403667216,
        0.42010518318170414,
        -2.1077984730016968
      ],
      "pass_index": 0,
      "pass_seed": 401010,
      "sampled_yaw_rad": -1.3079686152925298,
      "target_point": {
        "x": 0.38737102301538456,
        "y": -0.36265675272233033,
        "z": 0.5821005223025626
      },
      "tip_link": "panda_link8"
    },
    {
      "attempt": 27,
      "attempt_global": 27,
      "index": 26,
      "joint_names": [
        "panda_joint1",
        "panda_joint2",
        "panda_joint3",
        "panda_joint4",
        "panda_joint5",
        "panda_joint6",
        "panda_joint7"
      ],
      "joint_positions": [
        0.20878918890856107,
        1.4608886114543418,
        -2.3099760307137336,
        -1.668260719584525,
        1.33778894915296,
        0.8555998104013167,
        -2.112460390800763
      ],
      "pass_index": 0,
      "pass_seed": 401010,
      "sampled_yaw_rad": -1.3079686152925298,
      "target_point": {
        "x": 0.38737102301538456,
        "y": -0.36265675272233033,
        "z": 0.5821005223025626
      },
      "tip_link": "panda_link8"
    },
    {
      "attempt": 30,
      "attempt_global": 30,
      "index": 27,
      "joint_names": [
        "panda_joint1",
        "panda_joint2",
        "panda_joint3",
        "panda_joint4",
        "panda_joint5",
        "panda_joint6",
        "panda_joint7"
      ],
      "joint_positions": [
        0.16257487842751134,
        1.5081066170638813,
        -2.3559852717257947,
        -1.6647789481733068,
        1.3906049415612507,
        0.8001805497812186,
        -2.1243866443599555
      ],
      "pass_index": 0,
      "pass_seed": 401010,
      "sampled_yaw_rad": -1.3079686152925298,
      "target_point": {
        "x": 0.38737102301538456,
        "y": -0.36265675272233033,
        "z": 0.5821005223025626
      },
      "tip_link": "panda_link8"
    },
    {
      "attempt": 31,
      "attempt_global": 31,
      "index": 28,
      "joint_names": [
        "panda_joint1",
        "panda_joint2",
        "panda_joint3",
        "panda_joint4",
        "panda_joint5",
        "panda_joint6",
        "panda_joint7"
      ],
      "joint_positions": [
        -0.1515265585230959,
        1.7374288016710588,
        -2.6747617114773394,
        -1.6649663121895881,
        1.7541932670265825,
        0.468327752494912,
        -2.123745378794422
      ],
      "pass_index": 0,
      "pass_seed": 401010,
      "sampled_yaw_rad": -1.3079686152925298,
      "target_point": {
        "x": 0.38737102301538456,
        "y": -0.36265675272233033,
        "z": 0.5821005223025626
      },
      "tip_link": "panda_link8"
    },
    {
      "attempt": 32,
      "attempt_global": 32,
      "index": 29,
      "joint_names": [
        "panda_joint1",
        "panda_joint2",
        "panda_joint3",
        "panda_joint4",
        "panda_joint5",
        "panda_joint6",
        "panda_joint7"
      ],
      "joint_positions": [
        0.158018723569202,
        1.5125501282961293,
        -2.360549435878999,
        -1.6644819000376607,
        1.3957749817773568,
        0.7948100455417901,
        -2.125398077813631
      ],
      "pass_index": 0,
      "pass_seed": 401010,
      "sampled_yaw_rad": -1.3079686152925298,
      "target_point": {
        "x": 0.38737102301538456,
        "y": -0.36265675272233033,
        "z": 0.5821005223025626
      },
      "tip_link": "panda_link8"
    },
    {
      "attempt": 33,
      "attempt_global": 33,
      "index": 30,
      "joint_names": [
        "panda_joint1",
        "panda_joint2",
        "panda_joint3",
        "panda_joint4",
        "panda_joint5",
        "panda_joint6",
        "panda_joint7"
      ],
      "joint_positions": [
        -0.5643221422289573,
        -0.09925226224030965,
        -0.17760978190186918,
        -1.7944341611770092,
        -0.017647487902620173,
        1.6967138572031373,
        -0.7708987989508614
      ],
      "pass_index": 0,
      "pass_seed": 401010,
      "sampled_yaw_rad": -0.8170393265299118,
      "target_point": {
        "x": 0.38737102301538456,
        "y": -0.36265675272233033,
        "z": 0.5821005223025626
      },
      "tip_link": "panda_link8"
    },
    {
      "attempt": 34,
      "attempt_global": 34,
      "index": 31,
      "joint_names": [
        "panda_joint1",
        "panda_joint2",
        "panda_joint3",
        "panda_joint4",
        "panda_joint5",
        "panda_joint6",
        "panda_joint7"
      ],
      "joint_positions": [
        -0.9806925786257146,
        -0.10004298322349714,
        0.21539658207623602,
        -1.7944172780383771,
        0.021518845119946978,
        1.6966424122789538,
        -0.8010808964559234
      ],
      "pass_index": 0,
      "pass_seed": 401010,
      "sampled_yaw_rad": -0.8170393265299118,
      "target_point": {
        "x": 0.38737102301538456,
        "y": -0.36265675272233033,
        "z": 0.5821005223025626
      },
      "tip_link": "panda_link8"
    },
    {
      "attempt": 35,
      "attempt_global": 35,
      "index": 32,
      "joint_names": [
        "panda_joint1",
        "panda_joint2",
        "panda_joint3",
        "panda_joint4",
        "panda_joint5",
        "panda_joint6",
        "panda_joint7"
      ],
      "joint_positions": [
        -0.8933145180060514,
        -0.09854737405452038,
        0.13301137367591173,
        -1.7944843216292352,
        0.013153670467013455,
        1.696791613010452,
        -0.794631030794062
      ],
      "pass_index": 0,
      "pass_seed": 401010,
      "sampled_yaw_rad": -0.8170393265299118,
      "target_point": {
        "x": 0.38737102301538456,
        "y": -0.36265675272233033,
        "z": 0.5821005223025626
      },
      "tip_link": "panda_link8"
    },
    {
      "attempt": 36,
      "attempt_global": 36,
      "index": 33,
      "joint_names": [
        "panda_joint1",
        "panda_joint2",
        "panda_joint3",
        "panda_joint4",
        "panda_joint5",
        "panda_joint6",
        "panda_joint7"
      ],
      "joint_positions": [
        -0.4618455185975439,
        -0.10160487366590858,
        -0.2741008734064227,
        -1.794383903062381,
        -0.027677132520803092,
        1.6964997931148238,
        -0.7631704406546846
      ],
      "pass_index": 0,
      "pass_seed": 401010,
      "sampled_yaw_rad": -0.8170393265299118,
      "target_point": {
        "x": 0.38737102301538456,
        "y": -0.36265675272233033,
        "z": 0.5821005223025626
      },
      "tip_link": "panda_link8"
    },
    {
      "attempt": 37,
      "attempt_global": 37,
      "index": 34,
      "joint_names": [
        "panda_joint1",
        "panda_joint2",
        "panda_joint3",
        "panda_joint4",
        "panda_joint5",
        "panda_joint6",
        "panda_joint7"
      ],
      "joint_positions": [
        -1.0654260308719516,
        -0.1022670628542375,
        0.2951082004135395,
        -1.794369084558486,
        0.02993225700740143,
        1.6964384346422656,
        -0.8075636477133646
      ],
      "pass_index": 0,
      "pass_seed": 401010,
      "sampled_yaw_rad": -0.8170393265299118,
      "target_point": {
        "x": 0.38737102301538456,
        "y": -0.36265675272233033,
        "z": 0.5821005223025626
      },
      "tip_link": "panda_link8"
    },
    {
      "attempt": 38,
      "attempt_global": 38,
      "index": 35,
      "joint_names": [
        "panda_joint1",
        "panda_joint2",
        "panda_joint3",
        "panda_joint4",
        "panda_joint5",
        "panda_joint6",
        "panda_joint7"
      ],
      "joint_positions": [
        -0.13168231252018206,
        -0.11818482171256307,
        -0.5817454107829707,
        -1.793993737877149,
        -0.06533770154569353,
        1.6948484337932042,
        -0.7341619368643753
      ],
      "pass_index": 0,
      "pass_seed": 401010,
      "sampled_yaw_rad": -0.8170393265299118,
      "target_point": {
        "x": 0.38737102301538456,
        "y": -0.36265675272233033,
        "z": 0.5821005223025626
      },
      "tip_link": "panda_link8"
    },
    {
      "attempt": 39,
      "attempt_global": 39,
      "index": 36,
      "joint_names": [
        "panda_joint1",
        "panda_joint2",
        "panda_joint3",
        "panda_joint4",
        "panda_joint5",
        "panda_joint6",
        "panda_joint7"
      ],
      "joint_positions": [
        -0.5339664496504938,
        -0.09983592178722288,
        -0.20621998598176064,
        -1.7944217128046691,
        -0.02057278690476189,
        1.6966611756530867,
        -0.7686446361592117
      ],
      "pass_index": 0,
      "pass_seed": 401010,
      "sampled_yaw_rad": -0.8170393265299118,
      "target_point": {
        "x": 0.38737102301538456,
        "y": -0.36265675272233033,
        "z": 0.5821005223025626
      },
      "tip_link": "panda_link8"
    },
    {
      "attempt": 40,
      "attempt_global": 40,
      "index": 37,
      "joint_names": [
        "panda_joint1",
        "panda_joint2",
        "panda_joint3",
        "panda_joint4",
        "panda_joint5",
        "panda_joint6",
        "panda_joint7"
      ],
      "joint_positions": [
        -1.1339351448369357,
        -0.10465845703436874,
        0.35937314036738194,
        -1.79431611206715,
        0.03703924085752125,
        1.696214142768175,
        -0.8130392310796448
      ],
      "pass_index": 0,
      "pass_seed": 401010,
      "sampled_yaw_rad": -0.8170393265299118,
      "target_point": {
        "x": 0.38737102301538456,
        "y": -0.36265675272233033,
        "z": 0.5821005223025626
      },
      "tip_link": "panda_link8"
    },
    {
      "attempt": 41,
      "attempt_global": 41,
      "index": 38,
      "joint_names": [
        "panda_joint1",
        "panda_joint2",
        "panda_joint3",
        "panda_joint4",
        "panda_joint5",
        "panda_joint6",
        "panda_joint7"
      ],
      "joint_positions": [
        -0.8143835548710183,
        -0.09779209566696005,
        0.058492933435995216,
        -1.7944770246865578,
        0.005753800914501771,
        1.69684930668261,
        -0.788931166916975
      ],
      "pass_index": 0,
      "pass_seed": 401010,
      "sampled_yaw_rad": -0.8170393265299118,
      "target_point": {
        "x": 0.38737102301538456,
        "y": -0.36265675272233033,
        "z": 0.5821005223025626
      },
      "tip_link": "panda_link8"
    },
    {
      "attempt": 42,
      "attempt_global": 42,
      "index": 39,
      "joint_names": [
        "panda_joint1",
        "panda_joint2",
        "panda_joint3",
        "panda_joint4",
        "panda_joint5",
        "panda_joint6",
        "panda_joint7"
      ],
      "joint_positions": [
        -0.8623179549406383,
        -0.09817952073051407,
        0.10375559728398957,
        -1.7944807854075842,
        0.010234040483452276,
        1.6968197817716384,
        -0.7923824401484553
      ],
      "pass_index": 0,
      "pass_seed": 401010,
      "sampled_yaw_rad": -0.8170393265299118,
      "target_point": {
        "x": 0.38737102301538456,
        "y": -0.36265675272233033,
        "z": 0.5821005223025626
      },
      "tip_link": "panda_link8"
    },
    {
      "attempt": 43,
      "attempt_global": 43,
      "index": 40,
      "joint_names": [
        "panda_joint1",
        "panda_joint2",
        "panda_joint3",
        "panda_joint4",
        "panda_joint5",
        "panda_joint6",
        "panda_joint7"
      ],
      "joint_positions": [
        1.2272346842131097,
        -1.207511178111175,
        -1.021035644474479,
        -1.6929722767123474,
        -1.0934742298283762,
        1.1135983175759445,
        0.45856610645170737
      ],
      "pass_index": 0,
      "pass_seed": 401010,
      "sampled_yaw_rad": -0.3216447223486343,
      "target_point": {
        "x": 0.38737102301538456,
        "y": -0.36265675272233033,
        "z": 0.5821005223025626
      },
      "tip_link": "panda_link8"
    },
    {
      "attempt": 44,
      "attempt_global": 44,
      "index": 41,
      "joint_names": [
        "panda_joint1",
        "panda_joint2",
        "panda_joint3",
        "panda_joint4",
        "panda_joint5",
        "panda_joint6",
        "panda_joint7"
      ],
      "joint_positions": [
        1.0724298574755078,
        -0.9604640920887176,
        -1.1433164744162925,
        -1.721179497824175,
        -0.8791230098559404,
        1.3180857956166199,
        0.34338684212917325
      ],
      "pass_index": 0,
      "pass_seed": 401010,
      "sampled_yaw_rad": -0.3216447223486343,
      "target_point": {
        "x": 0.38737102301538456,
        "y": -0.36265675272233033,
        "z": 0.5821005223025626
      },
      "tip_link": "panda_link8"
    },
    {
      "attempt": 45,
      "attempt_global": 45,
      "index": 42,
      "joint_names": [
        "panda_joint1",
        "panda_joint2",
        "panda_joint3",
        "panda_joint4",
        "panda_joint5",
        "panda_joint6",
        "panda_joint7"
      ],
      "joint_positions": [
        1.1738963365201114,
        -1.1267993504482492,
        -1.0665464398939635,
        -1.7019920758625295,
        -1.0224641498257305,
        1.1849277854645486,
        0.4235939170795546
      ],
      "pass_index": 0,
      "pass_seed": 401010,
      "sampled_yaw_rad": -0.3216447223486343,
      "target_point": {
        "x": 0.38737102301538456,
        "y": -0.36265675272233033,
        "z": 0.5821005223025626
      },
      "tip_link": "panda_link8"
    },
    {
      "attempt": 46,
      "attempt_global": 46,
      "index": 43,
      "joint_names": [
        "panda_joint1",
        "panda_joint2",
        "panda_joint3",
        "panda_joint4",
        "panda_joint5",
        "panda_joint6",
        "panda_joint7"
      ],
      "joint_positions": [
        0.9696362644565468,
        -0.7833216571107853,
        -1.2019521845968382,
        -1.7415790961836473,
        -0.7259377840542012,
        1.4401421902348617,
        0.24645347728694847
      ],
      "pass_index": 0,
      "pass_seed": 401010,
      "sampled_yaw_rad": -0.3216447223486343,
      "target_point": {
        "x": 0.38737102301538456,
        "y": -0.36265675272233033,
        "z": 0.5821005223025626
      },
      "tip_link": "panda_link8"
    },
    {
      "attempt": 47,
      "attempt_global": 47,
      "index": 44,
      "joint_names": [
        "panda_joint1",
        "panda_joint2",
        "panda_joint3",
        "panda_joint4",
        "panda_joint5",
        "panda_joint6",
        "panda_joint7"
      ],
      "joint_positions": [
        0.9639286488269406,
        -0.773533918495067,
        -1.2044833500936525,
        -1.74268031721116,
        -0.717367878257631,
        1.446285804246669,
        0.24075561007264917
      ],
      "pass_index": 0,
      "pass_seed": 401010,
      "sampled_yaw_rad": -0.3216447223486343,
      "target_point": {
        "x": 0.38737102301538456,
        "y": -0.36265675272233033,
        "z": 0.5821005223025626
      },
      "tip_link": "panda_link8"
    },
    {
      "attempt": 48,
      "attempt_global": 48,
      "index": 45,
      "joint_names": [
        "panda_joint1",
        "panda_joint2",
        "panda_joint3",
        "panda_joint4",
        "panda_joint5",
        "panda_joint6",
        "panda_joint7"
      ],
      "joint_positions": [
        1.4065119406837334,
        -1.437690544915125,
        -0.8526943750183568,
        -1.670152455448123,
        -1.3130641948208692,
        0.8818085794988417,
        0.5413706847728211
      ],
      "pass_index": 0,
      "pass_seed": 401010,
      "sampled_yaw_rad": -0.3216447223486343,
      "target_point": {
        "x": 0.38737102301538456,
        "y": -0.36265675272233033,
        "z": 0.5821005223025626
      },
      "tip_link": "panda_link8"
    },
    {
      "attempt": 49,
      "attempt_global": 49,
      "index": 46,
      "joint_names": [
        "panda_joint1",
        "panda_joint2",
        "panda_joint3",
        "panda_joint4",
        "panda_joint5",
        "panda_joint6",
        "panda_joint7"
      ],
      "joint_positions": [
        1.0375318247542575,
        -0.9006173106021115,
        -1.1657753460338531,
        -1.728137259602179,
        -0.8276713071426793,
        1.3616030036662783,
        0.3119538044558794
      ],
      "pass_index": 0,
      "pass_seed": 401010,
      "sampled_yaw_rad": -0.3216447223486343,
      "target_point": {
        "x": 0.38737102301538456,
        "y": -0.36265675272233033,
        "z": 0.5821005223025626
      },
      "tip_link": "panda_link8"
    },
    {
      "attempt": 50,
      "attempt_global": 50,
      "index": 47,
      "joint_names": [
        "panda_joint1",
        "panda_joint2",
        "panda_joint3",
        "panda_joint4",
        "panda_joint5",
        "panda_joint6",
        "panda_joint7"
      ],
      "joint_positions": [
        1.1330666057476984,
        -1.061616820732635,
        -1.0992239371268346,
        -1.7094406301755547,
        -0.9660398634918717,
        1.2392714617457532,
        0.3934340126890669
      ],
      "pass_index": 0,
      "pass_seed": 401010,
      "sampled_yaw_rad": -0.3216447223486343,
      "target_point": {
        "x": 0.38737102301538456,
        "y": -0.36265675272233033,
        "z": 0.5821005223025626
      },
      "tip_link": "panda_link8"
    },
    {
      "attempt": 51,
      "attempt_global": 51,
      "index": 48,
      "joint_names": [
        "panda_joint1",
        "panda_joint2",
        "panda_joint3",
        "panda_joint4",
        "panda_joint5",
        "panda_joint6",
        "panda_joint7"
      ],
      "joint_positions": [
        1.1156863101260603,
        -1.0330968616399971,
        -1.112450352961327,
        -1.712737725185092,
        -0.9414928850667401,
        1.2621661311997028,
        0.37971864423834173
      ],
      "pass_index": 0,
      "pass_seed": 401010,
      "sampled_yaw_rad": -0.3216447223486343,
      "target_point": {
        "x": 0.38737102301538456,
        "y": -0.36265675272233033,
        "z": 0.5821005223025626
      },
      "tip_link": "panda_link8"
    },
    {
      "attempt": 52,
      "attempt_global": 52,
      "index": 49,
      "joint_names": [
        "panda_joint1",
        "panda_joint2",
        "panda_joint3",
        "panda_joint4",
        "panda_joint5",
        "panda_joint6",
        "panda_joint7"
      ],
      "joint_positions": [
        1.4720457874987596,
        -1.5060945875732816,
        -0.787660355061716,
        -1.664919503240139,
        -1.3882740966235891,
        0.8026048483508607,
        0.559391763152982
      ],
      "pass_index": 0,
      "pass_seed": 401010,
      "sampled_yaw_rad": -0.3216447223486343,
      "target_point": {
        "x": 0.38737102301538456,
        "y": -0.36265675272233033,
        "z": 0.5821005223025626
      },
      "tip_link": "panda_link8"
    },
    {
      "attempt": 53,
      "attempt_global": 53,
      "index": 50,
      "joint_names": [
        "panda_joint1",
        "panda_joint2",
        "panda_joint3",
        "panda_joint4",
        "panda_joint5",
        "panda_joint6",
        "panda_joint7"
      ],
      "joint_positions": [
        -2.6166047657112905,
        -1.0264750202384203,
        1.1154307602758555,
        -1.713505297890689,
        0.9358009784299963,
        1.2674058930130307,
        -0.05328430195639964
      ],
      "pass_index": 0,
      "pass_seed": 401010,
      "sampled_yaw_rad": 0.5797678341227597,
      "target_point": {
        "x": 0.38737102301538456,
        "y": -0.36265675272233033,
        "z": 0.5821005223025626
      },
      "tip_link": "panda_link8"
    },
    {
      "attempt": 54,
      "attempt_global": 54,
      "index": 51,
      "joint_names": [
        "panda_joint1",
        "panda_joint2",
        "panda_joint3",
        "panda_joint4",
        "panda_joint5",
        "panda_joint6",
        "panda_joint7"
      ],
      "joint_positions": [
        -2.3800811970837144,
        -0.6269066539347153,
        1.2321744344011243,
        -1.7585411637225585,
        0.5869025202461103,
        1.5304910863660672,
        0.17206681329824264
      ],
      "pass_index": 0,
      "pass_seed": 401010,
      "sampled_yaw_rad": 0.5797678341227597,
      "target_point": {
        "x": 0.38737102301538456,
        "y": -0.36265675272233033,
        "z": 0.5821005223025626
      },
      "tip_link": "panda_link8"
    },
    {
      "attempt": 55,
      "attempt_global": 55,
      "index": 52,
      "joint_names": [
        "panda_joint1",
        "panda_joint2",
        "panda_joint3",
        "panda_joint4",
        "panda_joint5",
        "panda_joint6",
        "panda_joint7"
      ],
      "joint_positions": [
        -2.394335851625731,
        -0.6494831868476282,
        1.2292807966769888,
        -1.7561927776110644,
        0.6072745638490623,
        1.5185018458597992,
        0.15775020284047164
      ],
      "pass_index": 0,
      "pass_seed": 401010,
      "sampled_yaw_rad": 0.5797678341227597,
      "target_point": {
        "x": 0.38737102301538456,
        "y": -0.36265675272233033,
        "z": 0.5821005223025626
      },
      "tip_link": "panda_link8"
    },
    {
      "attempt": 56,
      "attempt_global": 56,
      "index": 53,
      "joint_names": [
        "panda_joint1",
        "panda_joint2",
        "panda_joint3",
        "panda_joint4",
        "panda_joint5",
        "panda_joint6",
        "panda_joint7"
      ],
      "joint_positions": [
        -2.413303043609835,
        -0.6802044666363355,
        1.2244824241807484,
        -1.7529358397723676,
        0.6348188145593423,
        1.5016081424007826,
        0.13857051428512804
      ],
      "pass_index": 0,
      "pass_seed": 401010,
      "sampled_yaw_rad": 0.5797678341227597,
      "target_point": {
        "x": 0.38737102301538456,
        "y": -0.36265675272233033,
        "z": 0.5821005223025626
      },
      "tip_link": "panda_link8"
    },
    {
      "attempt": 57,
      "attempt_global": 57,
      "index": 54,
      "joint_names": [
        "panda_joint1",
        "panda_joint2",
        "panda_joint3",
        "panda_joint4",
        "panda_joint5",
        "panda_joint6",
        "panda_joint7"
      ],
      "joint_positions": [
        -2.5911267802266593,
        -0.9838258806018272,
        1.1338236948581006,
        -1.7184609707945553,
        0.8991772087752983,
        1.3004718440041645,
        -0.0320857655920888
      ],
      "pass_index": 0,
      "pass_seed": 401010,
      "sampled_yaw_rad": 0.5797678341227597,
      "target_point": {
        "x": 0.38737102301538456,
        "y": -0.36265675272233033,
        "z": 0.5821005223025626
      },
      "tip_link": "panda_link8"
    },
    {
      "attempt": 58,
      "attempt_global": 58,
      "index": 55,
      "joint_names": [
        "panda_joint1",
        "panda_joint2",
        "panda_joint3",
        "panda_joint4",
        "panda_joint5",
        "panda_joint6",
        "panda_joint7"
      ],
      "joint_positions": [
        -2.8973,
        -1.4218764357330584,
        0.8665418318466096,
        -1.6715047886284933,
        1.296597315589596,
        0.8993245671073217,
        -0.21346340872452194
      ],
      "pass_index": 0,
      "pass_seed": 401010,
      "sampled_yaw_rad": 0.5797678341227597,
      "target_point": {
        "x": 0.38737102301538456,
        "y": -0.36265675272233033,
        "z": 0.5821005223025626
      },
      "tip_link": "panda_link8"
    },
    {
      "attempt": 59,
      "attempt_global": 59,
      "index": 56,
      "joint_names": [
        "panda_joint1",
        "panda_joint2",
        "panda_joint3",
        "panda_joint4",
        "panda_joint5",
        "panda_joint6",
        "panda_joint7"
      ],
      "joint_positions": [
        -2.806394820350126,
        -1.3106676578086938,
        0.9535940692797038,
        -1.6820538563300567,
        1.187574682638816,
        1.0154122502753933,
        -0.1759204342276465
      ],
      "pass_index": 0,
      "pass_seed": 401010,
      "sampled_yaw_rad": 0.5797678341227597,
      "target_point": {
        "x": 0.38737102301538456,
        "y": -0.36265675272233033,
        "z": 0.5821005223025626
      },
      "tip_link": "panda_link8"
    },
    {
      "attempt": 60,
      "attempt_global": 60,
      "index": 57,
      "joint_names": [
        "panda_joint1",
        "panda_joint2",
        "panda_joint3",
        "panda_joint4",
        "panda_joint5",
        "panda_joint6",
        "panda_joint7"
      ],
      "joint_positions": [
        -2.710802525079444,
        -1.1758353101583814,
        1.0395985413157158,
        -1.6964697664500452,
        1.0654078053233478,
        1.1421381630825929,
        -0.12195672448725486
      ],
      "pass_index": 0,
      "pass_seed": 401010,
      "sampled_yaw_rad": 0.5797678341227597,
      "target_point": {
        "x": 0.38737102301538456,
        "y": -0.36265675272233033,
        "z": 0.5821005223025626
      },
      "tip_link": "panda_link8"
    },
    {
      "attempt": 62,
      "attempt_global": 62,
      "index": 58,
      "joint_names": [
        "panda_joint1",
        "panda_joint2",
        "panda_joint3",
        "panda_joint4",
        "panda_joint5",
        "panda_joint6",
        "panda_joint7"
      ],
      "joint_positions": [
        -2.3043386446616556,
        -0.5160866019787325,
        1.2371515309772583,
        -1.7693789454335993,
        0.4851121653222252,
        1.5839491116378668,
        0.24507586108875587
      ],
      "pass_index": 0,
      "pass_seed": 401010,
      "sampled_yaw_rad": 0.5797678341227597,
      "target_point": {
        "x": 0.38737102301538456,
        "y": -0.36265675272233033,
        "z": 0.5821005223025626
      },
      "tip_link": "panda_link8"
    },
    {
      "attempt": 63,
      "attempt_global": 63,
      "index": 59,
      "joint_names": [
        "panda_joint1",
        "panda_joint2",
        "panda_joint3",
        "panda_joint4",
        "panda_joint5",
        "panda_joint6",
        "panda_joint7"
      ],
      "joint_positions": [
        -2.5009489705955406,
        -0.8288334153131723,
        1.1891753239531333,
        -1.736409793500901,
        0.7656038763363789,
        1.4107392852621221,
        0.05072682143117955
      ],
      "pass_index": 0,
      "pass_seed": 401010,
      "sampled_yaw_rad": 0.5797678341227597,
      "target_point": {
        "x": 0.38737102301538456,
        "y": -0.36265675272233033,
        "z": 0.5821005223025626
      },
      "tip_link": "panda_link8"
    },
    {
      "attempt": 64,
      "attempt_global": 64,
      "index": 60,
      "joint_names": [
        "panda_joint1",
        "panda_joint2",
        "panda_joint3",
        "panda_joint4",
        "panda_joint5",
        "panda_joint6",
        "panda_joint7"
      ],
      "joint_positions": [
        -2.8973,
        -1.4218754057006289,
        0.8665425294864341,
        -1.6715038169398302,
        1.2965954581958004,
        0.8993256703540585,
        0.1492767931198176
      ],
      "pass_index": 0,
      "pass_seed": 401010,
      "sampled_yaw_rad": 0.9425066978066869,
      "target_point": {
        "x": 0.38737102301538456,
        "y": -0.36265675272233033,
        "z": 0.5821005223025626
      },
      "tip_link": "panda_link8"
    },
    {
      "attempt": 65,
      "attempt_global": 65,
      "index": 61,
      "joint_names": [
        "panda_joint1",
        "panda_joint2",
        "panda_joint3",
        "panda_joint4",
        "panda_joint5",
        "panda_joint6",
        "panda_joint7"
      ],
      "joint_positions": [
        -2.7367253270882683,
        -1.2141815726366345,
        1.0170055969945182,
        -1.6922432486577603,
        1.0994245239807388,
        1.1074957144356756,
        0.22460972315389047
      ],
      "pass_index": 0,
      "pass_seed": 401010,
      "sampled_yaw_rad": 0.9425066978066869,
      "target_point": {
        "x": 0.38737102301538456,
        "y": -0.36265675272233033,
        "z": 0.5821005223025626
      },
      "tip_link": "panda_link8"
    },
    {
      "attempt": 66,
      "attempt_global": 66,
      "index": 62,
      "joint_names": [
        "panda_joint1",
        "panda_joint2",
        "panda_joint3",
        "panda_joint4",
        "panda_joint5",
        "panda_joint6",
        "panda_joint7"
      ],
      "joint_positions": [
        -2.6422310837488268,
        -1.0685352262876255,
        1.0959111290030863,
        -1.7086563003819808,
        0.972003706586133,
        1.2336411513572807,
        0.2892248130617784
      ],
      "pass_index": 0,
      "pass_seed": 401010,
      "sampled_yaw_rad": 0.9425066978066869,
      "target_point": {
        "x": 0.38737102301538456,
        "y": -0.36265675272233033,
        "z": 0.5821005223025626
      },
      "tip_link": "panda_link8"
    },
    {
      "attempt": 67,
      "attempt_global": 67,
      "index": 63,
      "joint_names": [
        "panda_joint1",
        "panda_joint2",
        "panda_joint3",
        "panda_joint4",
        "panda_joint5",
        "panda_joint6",
        "panda_joint7"
      ],
      "joint_positions": [
        -2.7927692589341926,
        -1.2925644966267038,
        0.9662642565617539,
        -1.6839064008073192,
        1.1706859772831468,
        1.0332541468980074,
        0.19357374876959405
      ],
      "pass_index": 0,
      "pass_seed": 401010,
      "sampled_yaw_rad": 0.9425066978066869,
      "target_point": {
        "x": 0.38737102301538456,
        "y": -0.36265675272233033,
        "z": 0.5821005223025626
      },
      "tip_link": "panda_link8"
    },
    {
      "attempt": 68,
      "attempt_global": 68,
      "index": 64,
      "joint_names": [
        "panda_joint1",
        "panda_joint2",
        "panda_joint3",
        "panda_joint4",
        "panda_joint5",
        "panda_joint6",
        "panda_joint7"
      ],
      "joint_positions": [
        -2.1704562754776524,
        -0.3660498157455713,
        1.2053892543009206,
        -1.7817352700775995,
        0.3417469502486043,
        1.6413027352440634,
        0.7139240869370039
      ],
      "pass_index": 0,
      "pass_seed": 401010,
      "sampled_yaw_rad": 0.9425066978066869,
      "target_point": {
        "x": 0.38737102301538456,
        "y": -0.36265675272233033,
        "z": 0.5821005223025626
      },
      "tip_link": "panda_link8"
    },
    {
      "attempt": 69,
      "attempt_global": 69,
      "index": 65,
      "joint_names": [
        "panda_joint1",
        "panda_joint2",
        "panda_joint3",
        "panda_joint4",
        "panda_joint5",
        "panda_joint6",
        "panda_joint7"
      ],
      "joint_positions": [
        -1.7176665502996213,
        -0.16175598711711353,
        0.8894313548197649,
        -1.7926969051927932,
        0.12631051921099165,
        1.6893330234326271,
        0.8778184588568235
      ],
      "pass_index": 0,
      "pass_seed": 401010,
      "sampled_yaw_rad": 0.9425066978066869,
      "target_point": {
        "x": 0.38737102301538456,
        "y": -0.36265675272233033,
        "z": 0.5821005223025626
      },
      "tip_link": "panda_link8"
    },
    {
      "attempt": 70,
      "attempt_global": 70,
      "index": 66,
      "joint_names": [
        "panda_joint1",
        "panda_joint2",
        "panda_joint3",
        "panda_joint4",
        "panda_joint5",
        "panda_joint6",
        "panda_joint7"
      ],
      "joint_positions": [
        -2.6728589468429838,
        -1.117457646326532,
        1.0714434184882617,
        -1.7030459090636683,
        1.0143422852181112,
        1.192889792592189,
        0.2665693616651689
      ],
      "pass_index": 0,
      "pass_seed": 401010,
      "sampled_yaw_rad": 0.9425066978066869,
      "target_point": {
        "x": 0.38737102301538456,
        "y": -0.36265675272233033,
        "z": 0.5821005223025626
      },
      "tip_link": "panda_link8"
    },
    {
      "attempt": 71,
      "attempt_global": 71,
      "index": 67,
      "joint_names": [
        "panda_joint1",
        "panda_joint2",
        "panda_joint3",
        "panda_joint4",
        "panda_joint5",
        "panda_joint6",
        "panda_joint7"
      ],
      "joint_positions": [
        1.1058928156150305,
        -1.016844630904211,
        -1.1197051919234664,
        -1.714622518813501,
        -0.9275266055707545,
        1.2749753576350402,
        1.6359147031755266
      ],
      "pass_index": 0,
      "pass_seed": 401010,
      "sampled_yaw_rad": 0.9425066978066869,
      "target_point": {
        "x": 0.38737102301538456,
        "y": -0.36265675272233033,
        "z": 0.5821005223025626
      },
      "tip_link": "panda_link8"
    },
    {
      "attempt": 72,
      "attempt_global": 72,
      "index": 68,
      "joint_names": [
        "panda_joint1",
        "panda_joint2",
        "panda_joint3",
        "panda_joint4",
        "panda_joint5",
        "panda_joint6",
        "panda_joint7"
      ],
      "joint_positions": [
        1.467788068408896,
        -1.5018880342393586,
        -0.7919233828713503,
        -1.6652033190639057,
        -1.3834324689962099,
        0.8076491271949899,
        1.8225570480322415
      ],
      "pass_index": 0,
      "pass_seed": 401010,
      "sampled_yaw_rad": 0.9425066978066869,
      "target_point": {
        "x": 0.38737102301538456,
        "y": -0.36265675272233033,
        "z": 0.5821005223025626
      },
      "tip_link": "panda_link8"
    },
    {
      "attempt": 73,
      "attempt_global": 73,
      "index": 69,
      "joint_names": [
        "panda_joint1",
        "panda_joint2",
        "panda_joint3",
        "panda_joint4",
        "panda_joint5",
        "panda_joint6",
        "panda_joint7"
      ],
      "joint_positions": [
        2.8972243795723673,
        0.11068736075913492,
        2.664061895596837,
        -1.7941781375462056,
        -0.051187775528112434,
        1.6956269823179153,
        1.0144870718619923
      ],
      "pass_index": 0,
      "pass_seed": 401010,
      "sampled_yaw_rad": 0.9425066978066869,
      "target_point": {
        "x": 0.38737102301538456,
        "y": -0.36265675272233033,
        "z": 0.5821005223025626
      },
      "tip_link": "panda_link8"
    },
    {
      "attempt": 74,
      "attempt_global": 74,
      "index": 70,
      "joint_names": [
        "panda_joint1",
        "panda_joint2",
        "panda_joint3",
        "panda_joint4",
        "panda_joint5",
        "panda_joint6",
        "panda_joint7"
      ],
      "joint_positions": [
        0.573058486370241,
        0.9454302128258962,
        -1.9923829575535223,
        -1.722928910907936,
        0.8662124193248818,
        1.329234675595561,
        1.0326955678369978
      ],
      "pass_index": 0,
      "pass_seed": 401010,
      "sampled_yaw_rad": 1.6248752934652524,
      "target_point": {
        "x": 0.38737102301538456,
        "y": -0.36265675272233033,
        "z": 0.5821005223025626
      },
      "tip_link": "panda_link8"
    },
    {
      "attempt": 75,
      "attempt_global": 75,
      "index": 71,
      "joint_names": [
        "panda_joint1",
        "panda_joint2",
        "panda_joint3",
        "panda_joint4",
        "panda_joint5",
        "panda_joint6",
        "panda_joint7"
      ],
      "joint_positions": [
        0.31985709158063164,
        1.3306064821173489,
        -2.202403320771208,
        -1.6800573830555214,
        1.2064049757988549,
        0.9954430107817094,
        0.861938089878328
      ],
      "pass_index": 0,
      "pass_seed": 401010,
      "sampled_yaw_rad": 1.6248752934652524,
      "target_point": {
        "x": 0.38737102301538456,
        "y": -0.36265675272233033,
        "z": 0.5821005223025626
      },
      "tip_link": "panda_link8"
    },
    {
      "attempt": 76,
      "attempt_global": 76,
      "index": 72,
      "joint_names": [
        "panda_joint1",
        "panda_joint2",
        "panda_joint3",
        "panda_joint4",
        "panda_joint5",
        "panda_joint6",
        "panda_joint7"
      ],
      "joint_positions": [
        0.5980571217612528,
        0.9024892396728782,
        -1.976478356899709,
        -1.7279194114965544,
        0.8292833930194307,
        1.3602766071461867,
        1.0553559550689213
      ],
      "pass_index": 0,
      "pass_seed": 401010,
      "sampled_yaw_rad": 1.6248752934652524,
      "target_point": {
        "x": 0.38737102301538456,
        "y": -0.36265675272233033,
        "z": 0.5821005223025626
      },
      "tip_link": "panda_link8"
    },
    {
      "attempt": 77,
      "attempt_global": 77,
      "index": 73,
      "joint_names": [
        "panda_joint1",
        "panda_joint2",
        "panda_joint3",
        "panda_joint4",
        "panda_joint5",
        "panda_joint6",
        "panda_joint7"
      ],
      "joint_positions": [
        0.2518547339635106,
        1.4132497591186342,
        -2.267667512970432,
        -1.6722588166344428,
        1.2877361117668777,
        0.9087641586080762,
        0.8342851821114508
      ],
      "pass_index": 0,
      "pass_seed": 401010,
      "sampled_yaw_rad": 1.6248752934652524,
      "target_point": {
        "x": 0.38737102301538456,
        "y": -0.36265675272233033,
        "z": 0.5821005223025626
      },
      "tip_link": "panda_link8"
    },
    {
      "attempt": 78,
      "attempt_global": 78,
      "index": 74,
      "joint_names": [
        "panda_joint1",
        "panda_joint2",
        "panda_joint3",
        "panda_joint4",
        "panda_joint5",
        "panda_joint6",
        "panda_joint7"
      ],
      "joint_positions": [
        0.8216818348413524,
        0.5374606269958602,
        -1.9040256438117538,
        -1.7673854297808178,
        0.5049882206364154,
        1.574349438901674,
        1.2757513857415748
      ],
      "pass_index": 0,
      "pass_seed": 401010,
      "sampled_yaw_rad": 1.6248752934652524,
      "target_point": {
        "x": 0.38737102301538456,
        "y": -0.36265675272233033,
        "z": 0.5821005223025626
      },
      "tip_link": "panda_link8"
    },
    {
      "attempt": 79,
      "attempt_global": 79,
      "index": 75,
      "joint_names": [
        "panda_joint1",
        "panda_joint2",
        "panda_joint3",
        "panda_joint4",
        "panda_joint5",
        "panda_joint6",
        "panda_joint7"
      ],
      "joint_positions": [
        0.7850772336635591,
        0.590662078590407,
        -1.9059768540760105,
        -1.7622153502947577,
        0.5539458974428867,
        1.5489701410015,
        1.2405565459584926
      ],
      "pass_index": 0,
      "pass_seed": 401010,
      "sampled_yaw_rad": 1.6248752934652524,
      "target_point": {
        "x": 0.38737102301538456,
        "y": -0.36265675272233033,
        "z": 0.5821005223025626
      },
      "tip_link": "panda_link8"
    },
    {
      "attempt": 80,
      "attempt_global": 80,
      "index": 76,
      "joint_names": [
        "panda_joint1",
        "panda_joint2",
        "panda_joint3",
        "panda_joint4",
        "panda_joint5",
        "panda_joint6",
        "panda_joint7"
      ],
      "joint_positions": [
        0.5607643126578143,
        0.966382112017297,
        -2.000642050845552,
        -1.7204904645721266,
        0.8842037318613855,
        1.3136570293199648,
        1.021890870211544
      ],
      "pass_index": 0,
      "pass_seed": 401010,
      "sampled_yaw_rad": 1.6248752934652524,
      "target_point": {
        "x": 0.38737102301538456,
        "y": -0.36265675272233033,
        "z": 0.5821005223025626
      },
      "tip_link": "panda_link8"
    },
    {
      "attempt": 81,
      "attempt_global": 81,
      "index": 77,
      "joint_names": [
        "panda_joint1",
        "panda_joint2",
        "panda_joint3",
        "panda_joint4",
        "panda_joint5",
        "panda_joint6",
        "panda_joint7"
      ],
      "joint_positions": [
        0.7504403450637742,
        0.6443934378900441,
        -1.9116047183388911,
        -1.7567227939325036,
        0.6026892503480201,
        1.521235509340588,
        1.2060712262176725
      ],
      "pass_index": 0,
      "pass_seed": 401010,
      "sampled_yaw_rad": 1.6248752934652524,
      "target_point": {
        "x": 0.38737102301538456,
        "y": -0.36265675272233033,
        "z": 0.5821005223025626
      },
      "tip_link": "panda_link8"
    },
    {
      "attempt": 82,
      "attempt_global": 82,
      "index": 78,
      "joint_names": [
        "panda_joint1",
        "panda_joint2",
        "panda_joint3",
        "panda_joint4",
        "panda_joint5",
        "panda_joint6",
        "panda_joint7"
      ],
      "joint_positions": [
        0.4189117756695115,
        1.193566393973796,
        -2.1122694702768965,
        -1.6945053214242929,
        1.0810814534037538,
        1.126251504683925,
        0.9155952507409051
      ],
      "pass_index": 0,
      "pass_seed": 401010,
      "sampled_yaw_rad": 1.6248752934652524,
      "target_point": {
        "x": 0.38737102301538456,
        "y": -0.36265675272233033,
        "z": 0.5821005223025626
      },
      "tip_link": "panda_link8"
    },
    {
      "attempt": 83,
      "attempt_global": 83,
      "index": 79,
      "joint_names": [
        "panda_joint1",
        "panda_joint2",
        "panda_joint3",
        "panda_joint4",
        "panda_joint5",
        "panda_joint6",
        "panda_joint7"
      ],
      "joint_positions": [
        0.3913998953623791,
        1.2335885888973022,
        -2.1365594364683242,
        -1.6901379022479592,
        1.1168260562882488,
        1.0895534178663422,
        0.8990345754410162
      ],
      "pass_index": 0,
      "pass_seed": 401010,
      "sampled_yaw_rad": 1.6248752934652524,
      "target_point": {
        "x": 0.38737102301538456,
        "y": -0.36265675272233033,
        "z": 0.5821005223025626
      },
      "tip_link": "panda_link8"
    },
    {
      "attempt": 84,
      "attempt_global": 84,
      "index": 80,
      "joint_names": [
        "panda_joint1",
        "panda_joint2",
        "panda_joint3",
        "panda_joint4",
        "panda_joint5",
        "panda_joint6",
        "panda_joint7"
      ],
      "joint_positions": [
        0.4415496646137669,
        1.1595467650030393,
        -2.0928076508122535,
        -1.6982921476800592,
        1.0510840411364726,
        1.1565364119625268,
        1.475078703679062
      ],
      "pass_index": 0,
      "pass_seed": 401010,
      "sampled_yaw_rad": 2.169750253400421,
      "target_point": {
        "x": 0.38737102301538456,
        "y": -0.36265675272233033,
        "z": 0.5821005223025626
      },
      "tip_link": "panda_link8"
    },
    {
      "attempt": 85,
      "attempt_global": 85,
      "index": 81,
      "joint_names": [
        "panda_joint1",
        "panda_joint2",
        "panda_joint3",
        "panda_joint4",
        "panda_joint5",
        "panda_joint6",
        "panda_joint7"
      ],
      "joint_positions": [
        0.265119575234885,
        1.3978510127433,
        -2.2547729557758824,
        -1.6736382615208296,
        1.2721149861604202,
        0.9254204673925148,
        1.383996913076893
      ],
      "pass_index": 0,
      "pass_seed": 401010,
      "sampled_yaw_rad": 2.169750253400421,
      "target_point": {
        "x": 0.38737102301538456,
        "y": -0.36265675272233033,
        "z": 0.5821005223025626
      },
      "tip_link": "panda_link8"
    },
    {
      "attempt": 86,
      "attempt_global": 86,
      "index": 82,
      "joint_names": [
        "panda_joint1",
        "panda_joint2",
        "panda_joint3",
        "panda_joint4",
        "panda_joint5",
        "panda_joint6",
        "panda_joint7"
      ],
      "joint_positions": [
        0.6578916942149641,
        0.799059969802072,
        -1.9438773867432368,
        -1.7398035439309967,
        0.7396886755798133,
        1.430130621835529,
        1.6576451161141588
      ],
      "pass_index": 0,
      "pass_seed": 401010,
      "sampled_yaw_rad": 2.169750253400421,
      "target_point": {
        "x": 0.38737102301538456,
        "y": -0.36265675272233033,
        "z": 0.5821005223025626
      },
      "tip_link": "panda_link8"
    },
    {
      "attempt": 87,
      "attempt_global": 87,
      "index": 83,
      "joint_names": [
        "panda_joint1",
        "panda_joint2",
        "panda_joint3",
        "panda_joint4",
        "panda_joint5",
        "panda_joint6",
        "panda_joint7"
      ],
      "joint_positions": [
        0.6819276062391528,
        0.7578610295305441,
        -1.933231846132744,
        -1.7444426932125539,
        0.7036167950431517,
        1.4559921212824543,
        1.6816253890189596
      ],
      "pass_index": 0,
      "pass_seed": 401010,
      "sampled_yaw_rad": 2.169750253400421,
      "target_point": {
        "x": 0.38737102301538456,
        "y": -0.36265675272233033,
        "z": 0.5821005223025626
      },
      "tip_link": "panda_link8"
    },
    {
      "attempt": 88,
      "attempt_global": 88,
      "index": 84,
      "joint_names": [
        "panda_joint1",
        "panda_joint2",
        "panda_joint3",
        "panda_joint4",
        "panda_joint5",
        "panda_joint6",
        "panda_joint7"
      ],
      "joint_positions": [
        0.5380236782499458,
        1.004749215906602,
        -2.0166195030194713,
        -1.7160273371619175,
        0.9171390723046781,
        1.284397075083516,
        1.5474103994168495
      ],
      "pass_index": 0,
      "pass_seed": 401010,
      "sampled_yaw_rad": 2.169750253400421,
      "target_point": {
        "x": 0.38737102301538456,
        "y": -0.36265675272233033,
        "z": 0.5821005223025626
      },
      "tip_link": "panda_link8"
    },
    {
      "attempt": 89,
      "attempt_global": 89,
      "index": 85,
      "joint_names": [
        "panda_joint1",
        "panda_joint2",
        "panda_joint3",
        "panda_joint4",
        "panda_joint5",
        "panda_joint6",
        "panda_joint7"
      ],
      "joint_positions": [
        0.12428344911439021,
        1.544305166982669,
        -2.3944729414348105,
        -1.6625418362975604,
        1.4339143070744298,
        0.7555703415502839,
        1.3457391697154393
      ],
      "pass_index": 0,
      "pass_seed": 401010,
      "sampled_yaw_rad": 2.169750253400421,
      "target_point": {
        "x": 0.38737102301538456,
        "y": -0.36265675272233033,
        "z": 0.5821005223025626
      },
      "tip_link": "panda_link8"
    },
    {
      "attempt": 90,
      "attempt_global": 90,
      "index": 86,
      "joint_names": [
        "panda_joint1",
        "panda_joint2",
        "panda_joint3",
        "panda_joint4",
        "panda_joint5",
        "panda_joint6",
        "panda_joint7"
      ],
      "joint_positions": [
        0.7096778398909148,
        0.7109970788729452,
        -1.922844718968353,
        -1.749606495932553,
        0.6622326737860407,
        1.484014178826259,
        1.7096796071875773
      ],
      "pass_index": 0,
      "pass_seed": 401010,
      "sampled_yaw_rad": 2.169750253400421,
      "target_point": {
        "x": 0.38737102301538456,
        "y": -0.36265675272233033,
        "z": 0.5821005223025626
      },
      "tip_link": "panda_link8"
    },
    {
      "attempt": 91,
      "attempt_global": 91,
      "index": 87,
      "joint_names": [
        "panda_joint1",
        "panda_joint2",
        "panda_joint3",
        "panda_joint4",
        "panda_joint5",
        "panda_joint6",
        "panda_joint7"
      ],
      "joint_positions": [
        0.42992201107636396,
        1.1771402271752205,
        -2.102740467352211,
        -1.6963246448202407,
        1.066558314251149,
        1.1409766184711227,
        1.467465166313028
      ],
      "pass_index": 0,
      "pass_seed": 401010,
      "sampled_yaw_rad": 2.169750253400421,
      "target_point": {
        "x": 0.38737102301538456,
        "y": -0.36265675272233033,
        "z": 0.5821005223025626
      },
      "tip_link": "panda_link8"
    },
    {
      "attempt": 92,
      "attempt_global": 92,
      "index": 88,
      "joint_names": [
        "panda_joint1",
        "panda_joint2",
        "panda_joint3",
        "panda_joint4",
        "panda_joint5",
        "panda_joint6",
        "panda_joint7"
      ],
      "joint_positions": [
        0.2970513359565556,
        1.3593488458066934,
        -2.2240412152096707,
        -1.6772383198461756,
        1.2340424299892843,
        0.9660300493445588,
        1.3967420963124424
      ],
      "pass_index": 0,
      "pass_seed": 401010,
      "sampled_yaw_rad": 2.169750253400421,
      "target_point": {
        "x": 0.38737102301538456,
        "y": -0.36265675272233033,
        "z": 0.5821005223025626
      },
      "tip_link": "panda_link8"
    },
    {
      "attempt": 93,
      "attempt_global": 93,
      "index": 89,
      "joint_names": [
        "panda_joint1",
        "panda_joint2",
        "panda_joint3",
        "panda_joint4",
        "panda_joint5",
        "panda_joint6",
        "panda_joint7"
      ],
      "joint_positions": [
        0.6329502368963558,
        0.8421468719634095,
        -1.9564625771796214,
        -1.7348858924588957,
        0.7771563042781476,
        1.4018803559959776,
        1.633241742096976
      ],
      "pass_index": 0,
      "pass_seed": 401010,
      "sampled_yaw_rad": 2.169750253400421,
      "target_point": {
        "x": 0.38737102301538456,
        "y": -0.36265675272233033,
        "z": 0.5821005223025626
      },
      "tip_link": "panda_link8"
    },
    {
      "attempt": 94,
      "attempt_global": 94,
      "index": 90,
      "joint_names": [
        "panda_joint1",
        "panda_joint2",
        "panda_joint3",
        "panda_joint4",
        "panda_joint5",
        "panda_joint6",
        "panda_joint7"
      ],
      "joint_positions": [
        1.8171916486446775,
        -1.7518397311390805,
        -0.4376517112224685,
        -1.6673437675782365,
        -1.7910437903884442,
        0.44140111284389305,
        -2.799508051014528
      ],
      "pass_index": 0,
      "pass_seed": 401010,
      "sampled_yaw_rad": 2.610959355671749,
      "target_point": {
        "x": 0.38737102301538456,
        "y": -0.36265675272233033,
        "z": 0.5821005223025626
      },
      "tip_link": "panda_link8"
    },
    {
      "attempt": 95,
      "attempt_global": 95,
      "index": 91,
      "joint_names": [
        "panda_joint1",
        "panda_joint2",
        "panda_joint3",
        "panda_joint4",
        "panda_joint5",
        "panda_joint6",
        "panda_joint7"
      ],
      "joint_positions": [
        -1.9229391610176076,
        1.1948918417035919,
        2.113048667190971,
        -1.6943622831341298,
        -1.0822536627086121,
        1.1250578391112558,
        -2.8973
      ],
      "pass_index": 0,
      "pass_seed": 401010,
      "sampled_yaw_rad": 2.610959355671749,
      "target_point": {
        "x": 0.38737102301538456,
        "y": -0.36265675272233033,
        "z": 0.5821005223025626
      },
      "tip_link": "panda_link8"
    },
    {
      "attempt": 96,
      "attempt_global": 96,
      "index": 92,
      "joint_names": [
        "panda_joint1",
        "panda_joint2",
        "panda_joint3",
        "panda_joint4",
        "panda_joint5",
        "panda_joint6",
        "panda_joint7"
      ],
      "joint_positions": [
        1.493016530112322,
        -1.5263219192846196,
        -0.766623783269036,
        -1.66360805679923,
        -1.412049336062531,
        0.7779845633339421,
        -2.7867187514450285
      ],
      "pass_index": 0,
      "pass_seed": 401010,
      "sampled_yaw_rad": 2.610959355671749,
      "target_point": {
        "x": 0.38737102301538456,
        "y": -0.36265675272233033,
        "z": 0.5821005223025626
      },
      "tip_link": "panda_link8"
    },
    {
      "attempt": 97,
      "attempt_global": 97,
      "index": 93,
      "joint_names": [
        "panda_joint1",
        "panda_joint2",
        "panda_joint3",
        "panda_joint4",
        "panda_joint5",
        "panda_joint6",
        "panda_joint7"
      ],
      "joint_positions": [
        1.5589177415494284,
        -1.5848978878624784,
        -0.7000334323873554,
        -1.6606250069546542,
        -1.486303246127291,
        0.7029684325526645,
        -2.7766658372828616
      ],
      "pass_index": 0,
      "pass_seed": 401010,
      "sampled_yaw_rad": 2.610959355671749,
      "target_point": {
        "x": 0.38737102301538456,
        "y": -0.36265675272233033,
        "z": 0.5821005223025626
      },
      "tip_link": "panda_link8"
    },
    {
      "attempt": 98,
      "attempt_global": 98,
      "index": 94,
      "joint_names": [
        "panda_joint1",
        "panda_joint2",
        "panda_joint3",
        "panda_joint4",
        "panda_joint5",
        "panda_joint6",
        "panda_joint7"
      ],
      "joint_positions": [
        1.8406385685543598,
        -1.7628,
        -0.41417915086232293,
        -1.669610710129639,
        -1.821679113184355,
        0.4200547104050587,
        -2.8073329238424694
      ],
      "pass_index": 0,
      "pass_seed": 401010,
      "sampled_yaw_rad": 2.610959355671749,
      "target_point": {
        "x": 0.38737102301538456,
        "y": -0.36265675272233033,
        "z": 0.5821005223025626
      },
      "tip_link": "panda_link8"
    },
    {
      "attempt": 99,
      "attempt_global": 99,
      "index": 95,
      "joint_names": [
        "panda_joint1",
        "panda_joint2",
        "panda_joint3",
        "panda_joint4",
        "panda_joint5",
        "panda_joint6",
        "panda_joint7"
      ],
      "joint_positions": [
        1.5403057298571086,
        -1.569095814255682,
        -0.7189030564802718,
        -1.6612870173143164,
        -1.4653578961248188,
        0.7237988808903296,
        -2.778890374964239
      ],
      "pass_index": 0,
      "pass_seed": 401010,
      "sampled_yaw_rad": 2.610959355671749,
      "target_point": {
        "x": 0.38737102301538456,
        "y": -0.36265675272233033,
        "z": 0.5821005223025626
      },
      "tip_link": "panda_link8"
    },
    {
      "attempt": 100,
      "attempt_global": 100,
      "index": 96,
      "joint_names": [
        "panda_joint1",
        "panda_joint2",
        "panda_joint3",
        "panda_joint4",
        "panda_joint5",
        "panda_joint6",
        "panda_joint7"
      ],
      "joint_positions": [
        1.6082753577425253,
        -1.6241119429632835,
        -0.6498338472056714,
        -1.6595689734301555,
        -1.541996259039755,
        0.6490689946904367,
        -2.773125432613392
      ],
      "pass_index": 0,
      "pass_seed": 401010,
      "sampled_yaw_rad": 2.610959355671749,
      "target_point": {
        "x": 0.38737102301538456,
        "y": -0.36265675272233033,
        "z": 0.5821005223025626
      },
      "tip_link": "panda_link8"
    },
    {
      "attempt": 103,
      "attempt_global": 103,
      "index": 97,
      "joint_names": [
        "panda_joint1",
        "panda_joint2",
        "panda_joint3",
        "panda_joint4",
        "panda_joint5",
        "panda_joint6",
        "panda_joint7"
      ],
      "joint_positions": [
        1.486941085937418,
        -1.5205457529216482,
        -0.7727260838922518,
        -1.6639723437396,
        -1.405176917446387,
        0.7850772439152913,
        -2.78795126074842
      ],
      "pass_index": 0,
      "pass_seed": 401010,
      "sampled_yaw_rad": 2.610959355671749,
      "target_point": {
        "x": 0.38737102301538456,
        "y": -0.36265675272233033,
        "z": 0.5821005223025626
      },
      "tip_link": "panda_link8"
    },
    {
      "attempt": 104,
      "attempt_global": 104,
      "index": 98,
      "joint_names": [
        "panda_joint1",
        "panda_joint2",
        "panda_joint3",
        "panda_joint4",
        "panda_joint5",
        "panda_joint6",
        "panda_joint7"
      ],
      "joint_positions": [
        1.6652689734025512,
        -1.6647909108071286,
        -0.5917267623398477,
        -1.6596505768450966,
        -1.607084675483919,
        0.5892030502900082,
        -2.7733993586271453
      ],
      "pass_index": 0,
      "pass_seed": 401010,
      "sampled_yaw_rad": 2.610959355671749,
      "target_point": {
        "x": 0.38737102301538456,
        "y": -0.36265675272233033,
        "z": 0.5821005223025626
      },
      "tip_link": "panda_link8"
    },
    {
      "attempt": 106,
      "attempt_global": 106,
      "index": 99,
      "joint_names": [
        "panda_joint1",
        "panda_joint2",
        "panda_joint3",
        "panda_joint4",
        "panda_joint5",
        "panda_joint6",
        "panda_joint7"
      ],
      "joint_positions": [
        1.8195891020667667,
        -1.7529917371538266,
        -0.4352453884491064,
        -1.6675595687914637,
        -1.7941363060953044,
        0.43919873955200417,
        -2.800250015621305
      ],
      "pass_index": 0,
      "pass_seed": 401010,
      "sampled_yaw_rad": 2.610959355671749,
      "target_point": {
        "x": 0.38737102301538456,
        "y": -0.36265675272233033,
        "z": 0.5821005223025626
      },
      "tip_link": "panda_link8"
    }
  ]
}